[{"Renta sur 7 jours":94395940,"Renta du 27/06/2025":31385568,"Renta du 28/06/2025":20098412,"Renta du 29/06/2025":5407154,"Renta du 30/06/2025":3891459,"Renta du 01/07/2025":960241,"Renta du 02/07/2025":29423654,"Renta du 03/07/2025":3229452},{"Historique":[{"Id":1474,"Name":"Amulette de Xélor","CraftCost":8387,"RuneCost":0,"ResellPrice":127999,"Renta":119612,"Date":"27/06/2025"},{"Id":2531,"Name":"Caracoiffe","CraftCost":15271,"RuneCost":0,"ResellPrice":39998,"Renta":24727,"Date":"27/06/2025"},{"Id":6454,"Name":"Abraton Sombre","CraftCost":46338,"RuneCost":0,"ResellPrice":1228999,"Renta":1182661,"Date":"27/06/2025"},{"Id":8609,"Name":"Geish'Arc","CraftCost":65585,"RuneCost":0,"ResellPrice":98599,"Renta":33014,"Date":"27/06/2025"},{"Id":10848,"Name":"Bottes de Klüme","CraftCost":15891,"RuneCost":0,"ResellPrice":302999,"Renta":287108,"Date":"27/06/2025"},{"Id":6507,"Name":"Marteau de la Terps","CraftCost":40472,"RuneCost":0,"ResellPrice":69996,"Renta":29524,"Date":"27/06/2025"},{"Id":14003,"Name":"Bottes de Styx","CraftCost":276620,"RuneCost":0,"ResellPrice":448998,"Renta":172378,"Date":"27/06/2025"},{"Id":2638,"Name":"La Griffe Aiguisée","CraftCost":22448,"RuneCost":0,"ResellPrice":134999,"Renta":112551,"Date":"27/06/2025"},{"Id":6519,"Name":"Baguette de Kouartz","CraftCost":16870,"RuneCost":0,"ResellPrice":14698,"Renta":-2172,"Date":"27/06/2025"},{"Id":1083,"Name":"Marteau Pospodrol","CraftCost":9572,"RuneCost":0,"ResellPrice":21899,"Renta":12327,"Date":"27/06/2025"},{"Id":7161,"Name":"Arc Assin","CraftCost":31008,"RuneCost":0,"ResellPrice":69999,"Renta":38991,"Date":"27/06/2025"},{"Id":7213,"Name":"Pelle Rhon","CraftCost":80274,"RuneCost":0,"ResellPrice":169998,"Renta":89724,"Date":"27/06/2025"},{"Id":11352,"Name":"Bottes de Karotz","CraftCost":11056,"RuneCost":0,"ResellPrice":19998,"Renta":8942,"Date":"27/06/2025"},{"Id":7154,"Name":"Marteau M'Pouce","CraftCost":40807,"RuneCost":0,"ResellPrice":126999,"Renta":86192,"Date":"27/06/2025"},{"Id":7155,"Name":"Marteau Nairedeubrest","CraftCost":56144,"RuneCost":0,"ResellPrice":129997,"Renta":73853,"Date":"27/06/2025"},{"Id":13136,"Name":"Caskoffre","CraftCost":10759,"RuneCost":0,"ResellPrice":4999,"Renta":-5760,"Date":"27/06/2025"},{"Id":12031,"Name":"Geta de Logram","CraftCost":6392,"RuneCost":0,"ResellPrice":1260010,"Renta":1253618,"Date":"27/06/2025"},{"Id":12071,"Name":"Bottes de Nelween","CraftCost":12936,"RuneCost":0,"ResellPrice":8999,"Renta":-3937,"Date":"27/06/2025"},{"Id":6518,"Name":"Amrothiline","CraftCost":82353,"RuneCost":0,"ResellPrice":128999,"Renta":46646,"Date":"27/06/2025"},{"Id":15996,"Name":"Pendentif Curatif","CraftCost":407354,"RuneCost":0,"ResellPrice":499999,"Renta":92645,"Date":"27/06/2025"},{"Id":6472,"Name":"Dragocoiffe Argile","CraftCost":13516,"RuneCost":0,"ResellPrice":1098999,"Renta":1085483,"Date":"27/06/2025"},{"Id":2639,"Name":"Fausse Griffe de Ceangal","CraftCost":19081,"RuneCost":0,"ResellPrice":24997,"Renta":5916,"Date":"27/06/2025"},{"Id":6528,"Name":"Pelle Rinage","CraftCost":42204,"RuneCost":0,"ResellPrice":82199,"Renta":39995,"Date":"27/06/2025"},{"Id":2398,"Name":"L'Œil de Kanigrou","CraftCost":11164,"RuneCost":0,"ResellPrice":16999,"Renta":5835,"Date":"27/06/2025"},{"Id":11736,"Name":"Alliance Sorcelée","CraftCost":332174,"RuneCost":0,"ResellPrice":242999,"Renta":-89175,"Date":"27/06/2025"},{"Id":16173,"Name":"Anneau Tissé","CraftCost":24015,"RuneCost":0,"ResellPrice":46399,"Renta":22384,"Date":"27/06/2025"},{"Id":7144,"Name":"Blémiche","CraftCost":76617,"RuneCost":0,"ResellPrice":360999,"Renta":284382,"Date":"27/06/2025"},{"Id":6778,"Name":"Farlacoiffe","CraftCost":45114,"RuneCost":0,"ResellPrice":49999,"Renta":4885,"Date":"27/06/2025"},{"Id":6517,"Name":"Dagues Hischantes","CraftCost":18785,"RuneCost":0,"ResellPrice":34443,"Renta":15658,"Date":"27/06/2025"},{"Id":11719,"Name":"Cape du Glourséleste","CraftCost":573939,"RuneCost":0,"ResellPrice":789999,"Renta":216060,"Date":"27/06/2025"},{"Id":6743,"Name":"Fourballiance","CraftCost":60175,"RuneCost":0,"ResellPrice":89999,"Renta":29824,"Date":"27/06/2025"},{"Id":6834,"Name":"Coiffe du Chef Crocodaille","CraftCost":20775,"RuneCost":0,"ResellPrice":73999,"Renta":53224,"Date":"27/06/2025"},{"Id":6830,"Name":"Petit sac d'écolier du Chef Crocodaille","CraftCost":14545,"RuneCost":0,"ResellPrice":29999,"Renta":15454,"Date":"27/06/2025"},{"Id":8148,"Name":"Marteau du Craqueleur Légendaire","CraftCost":375589,"RuneCost":0,"ResellPrice":84999,"Renta":-290590,"Date":"27/06/2025"},{"Id":7513,"Name":"Sandales Titude","CraftCost":176462,"RuneCost":0,"ResellPrice":289999,"Renta":113537,"Date":"27/06/2025"},{"Id":1435,"Name":"La Pelle du Large","CraftCost":13877,"RuneCost":0,"ResellPrice":58299,"Renta":44422,"Date":"27/06/2025"},{"Id":4241,"Name":"Griffe Rose","CraftCost":63825,"RuneCost":0,"ResellPrice":40099,"Renta":-23726,"Date":"27/06/2025"},{"Id":15360,"Name":"Gruchaussures","CraftCost":313029,"RuneCost":0,"ResellPrice":439998,"Renta":126969,"Date":"27/06/2025"},{"Id":14053,"Name":"Bonnet Vicieux","CraftCost":1497501,"RuneCost":0,"ResellPrice":1249999,"Renta":-247502,"Date":"27/06/2025"},{"Id":14135,"Name":"Pelle Vice","CraftCost":1198343,"RuneCost":0,"ResellPrice":949999,"Renta":-248344,"Date":"27/06/2025"},{"Id":3206,"Name":"La Xerbo","CraftCost":15025,"RuneCost":0,"ResellPrice":13099,"Renta":-1926,"Date":"27/06/2025"},{"Id":17213,"Name":"Bottes des 1001 Griffes","CraftCost":16925,"RuneCost":0,"ResellPrice":39999,"Renta":23074,"Date":"27/06/2025"},{"Id":12371,"Name":"Cape du Gorgouille","CraftCost":35132,"RuneCost":0,"ResellPrice":362999,"Renta":327867,"Date":"27/06/2025"},{"Id":12109,"Name":"Anneau du Professeur Xa","CraftCost":332338,"RuneCost":0,"ResellPrice":279999,"Renta":-52339,"Date":"27/06/2025"},{"Id":12099,"Name":"Bâton des Prophètes","CraftCost":783789,"RuneCost":0,"ResellPrice":899999,"Renta":116210,"Date":"27/06/2025"},{"Id":12040,"Name":"Ceinture d'Hichète","CraftCost":12837,"RuneCost":0,"ResellPrice":27099,"Renta":14262,"Date":"27/06/2025"},{"Id":14519,"Name":"Marteau du Juge Lou","CraftCost":317053,"RuneCost":0,"ResellPrice":459999,"Renta":142946,"Date":"27/06/2025"},{"Id":7160,"Name":"Arc Hanne","CraftCost":182848,"RuneCost":0,"ResellPrice":278998,"Renta":96150,"Date":"27/06/2025"},{"Id":1651,"Name":"Le Cutter","CraftCost":10212,"RuneCost":0,"ResellPrice":416999,"Renta":406787,"Date":"27/06/2025"},{"Id":11386,"Name":"Bottoppinz","CraftCost":5001,"RuneCost":0,"ResellPrice":1033999,"Renta":1028998,"Date":"27/06/2025"},{"Id":15778,"Name":"Coiffe de Fraktale","CraftCost":261915,"RuneCost":0,"ResellPrice":319999,"Renta":58084,"Date":"27/06/2025"},{"Id":12029,"Name":"Amulette de Mirh","CraftCost":11684,"RuneCost":0,"ResellPrice":39997,"Renta":28313,"Date":"27/06/2025"},{"Id":8850,"Name":"Racine de Floribonde","CraftCost":179233,"RuneCost":0,"ResellPrice":194999,"Renta":15766,"Date":"27/06/2025"},{"Id":8610,"Name":"Le Kikoularc","CraftCost":9858,"RuneCost":0,"ResellPrice":23689,"Renta":13831,"Date":"27/06/2025"},{"Id":8611,"Name":"Bagdette Café","CraftCost":12935,"RuneCost":0,"ResellPrice":39999,"Renta":27064,"Date":"27/06/2025"},{"Id":2391,"Name":"Amulette de la Bouboule","CraftCost":26820,"RuneCost":0,"ResellPrice":24994,"Renta":-1826,"Date":"27/06/2025"},{"Id":13485,"Name":"Krosmangle","CraftCost":48991,"RuneCost":0,"ResellPrice":79999,"Renta":31008,"Date":"27/06/2025"},{"Id":250,"Name":"Ares","CraftCost":30846,"RuneCost":0,"ResellPrice":51899,"Renta":21053,"Date":"27/06/2025"},{"Id":14066,"Name":"Bottes de Nileza","CraftCost":809752,"RuneCost":0,"ResellPrice":1109999,"Renta":300247,"Date":"27/06/2025"},{"Id":18587,"Name":"Chaussquales","CraftCost":451338,"RuneCost":0,"ResellPrice":449999,"Renta":-1339,"Date":"27/06/2025"},{"Id":11583,"Name":"Bottes de l'Obsidiantre","CraftCost":560963,"RuneCost":0,"ResellPrice":889999,"Renta":329036,"Date":"27/06/2025"},{"Id":17120,"Name":"Amulette du K.O.","CraftCost":1512409,"RuneCost":0,"ResellPrice":1555553,"Renta":43144,"Date":"27/06/2025"},{"Id":7163,"Name":"Arc Huledela","CraftCost":145074,"RuneCost":0,"ResellPrice":94999,"Renta":-50075,"Date":"27/06/2025"},{"Id":8290,"Name":"Amulette du Dragoeuf","CraftCost":120110,"RuneCost":0,"ResellPrice":139999,"Renta":19889,"Date":"27/06/2025"},{"Id":270,"Name":"Xaveur","CraftCost":14421,"RuneCost":0,"ResellPrice":54399,"Renta":39978,"Date":"27/06/2025"},{"Id":14929,"Name":"Amulule","CraftCost":1331426,"RuneCost":0,"ResellPrice":1199998,"Renta":-131428,"Date":"27/06/2025"},{"Id":14156,"Name":"Rapière aux Glyphes","CraftCost":524075,"RuneCost":0,"ResellPrice":349997,"Renta":-174078,"Date":"27/06/2025"},{"Id":14273,"Name":"Slip du Roi de Bonta","CraftCost":1493605,"RuneCost":0,"ResellPrice":1395998,"Renta":-97607,"Date":"27/06/2025"},{"Id":13122,"Name":"Ceinture de Danathor","CraftCost":880126,"RuneCost":0,"ResellPrice":789999,"Renta":-90127,"Date":"27/06/2025"},{"Id":18430,"Name":"Masse Boulépique","CraftCost":25947,"RuneCost":0,"ResellPrice":24999,"Renta":-948,"Date":"27/06/2025"},{"Id":13018,"Name":"Bottoduvet","CraftCost":12151,"RuneCost":0,"ResellPrice":39998,"Renta":27847,"Date":"27/06/2025"},{"Id":9158,"Name":"Bloptes Griottes","CraftCost":4557,"RuneCost":0,"ResellPrice":9349,"Renta":4792,"Date":"27/06/2025"},{"Id":6477,"Name":"Chapeau du Mineur Sombre","CraftCost":73441,"RuneCost":0,"ResellPrice":230999,"Renta":157558,"Date":"27/06/2025"},{"Id":8117,"Name":"Scaracape Dorée","CraftCost":4559,"RuneCost":0,"ResellPrice":3999,"Renta":-560,"Date":"27/06/2025"},{"Id":1904,"Name":"Dragocoiffe Calcaire","CraftCost":10521,"RuneCost":0,"ResellPrice":1101999,"Renta":1091478,"Date":"27/06/2025"},{"Id":180,"Name":"La Baguette des Limbes","CraftCost":151981,"RuneCost":0,"ResellPrice":99999,"Renta":-51982,"Date":"27/06/2025"},{"Id":2597,"Name":"Hache de Brèche","CraftCost":10608,"RuneCost":0,"ResellPrice":14449,"Renta":3841,"Date":"27/06/2025"},{"Id":14931,"Name":"Chaussures Hau","CraftCost":797435,"RuneCost":0,"ResellPrice":944999,"Renta":147564,"Date":"27/06/2025"},{"Id":15773,"Name":"Coiffe de Soissanth","CraftCost":553569,"RuneCost":0,"ResellPrice":350999,"Renta":-202570,"Date":"27/06/2025"},{"Id":11715,"Name":"Coiffe de Kolosso","CraftCost":1215576,"RuneCost":0,"ResellPrice":2294999,"Renta":1079423,"Date":"27/06/2025"},{"Id":7195,"Name":"Karnak","CraftCost":128734,"RuneCost":0,"ResellPrice":99999,"Renta":-28735,"Date":"27/06/2025"},{"Id":9164,"Name":"Bloptes Coco Royales","CraftCost":12406,"RuneCost":0,"ResellPrice":17998,"Renta":5592,"Date":"27/06/2025"},{"Id":14883,"Name":"Bandeau Culaire","CraftCost":1389228,"RuneCost":0,"ResellPrice":2300000,"Renta":910772,"Date":"27/06/2025"},{"Id":1666,"Name":"Bottes de l'Apprenti Invocateur","CraftCost":13325,"RuneCost":0,"ResellPrice":28999,"Renta":15674,"Date":"27/06/2025"},{"Id":15780,"Name":"Ceinture de Fraktale","CraftCost":228185,"RuneCost":0,"ResellPrice":319999,"Renta":91814,"Date":"27/06/2025"},{"Id":7153,"Name":"Marteau Hubohu","CraftCost":88681,"RuneCost":0,"ResellPrice":144999,"Renta":56318,"Date":"27/06/2025"},{"Id":14009,"Name":"Willkillsano","CraftCost":310499,"RuneCost":0,"ResellPrice":588999,"Renta":278500,"Date":"27/06/2025"},{"Id":11746,"Name":"Marteau Reine","CraftCost":374096,"RuneCost":0,"ResellPrice":369999,"Renta":-4097,"Date":"27/06/2025"},{"Id":9161,"Name":"Bloptes Indigo","CraftCost":3067,"RuneCost":0,"ResellPrice":29999,"Renta":26932,"Date":"27/06/2025"},{"Id":7146,"Name":"La Bertheuze","CraftCost":42925,"RuneCost":0,"ResellPrice":45998,"Renta":3073,"Date":"27/06/2025"},{"Id":18775,"Name":"Chaussons du Comte Razof","CraftCost":515867,"RuneCost":0,"ResellPrice":498999,"Renta":-16868,"Date":"27/06/2025"},{"Id":11575,"Name":"Amulette du Royalmouth","CraftCost":90280,"RuneCost":0,"ResellPrice":119999,"Renta":29719,"Date":"27/06/2025"},{"Id":11573,"Name":"Chapeau de Ben le Ripate","CraftCost":130355,"RuneCost":0,"ResellPrice":144999,"Renta":14644,"Date":"27/06/2025"},{"Id":14499,"Name":"Bottes du Wabbit Céphale","CraftCost":133880,"RuneCost":0,"ResellPrice":199999,"Renta":66119,"Date":"27/06/2025"},{"Id":6742,"Name":"Fourbamulette","CraftCost":81723,"RuneCost":0,"ResellPrice":62998,"Renta":-18725,"Date":"27/06/2025"},{"Id":8291,"Name":"Bottes du Dragoeuf","CraftCost":106702,"RuneCost":0,"ResellPrice":119999,"Renta":13297,"Date":"27/06/2025"},{"Id":9152,"Name":"Amublop Indigo","CraftCost":5426,"RuneCost":0,"ResellPrice":8999,"Renta":3573,"Date":"27/06/2025"},{"Id":11634,"Name":"Bâton du Shamansot","CraftCost":107488,"RuneCost":0,"ResellPrice":139999,"Renta":32511,"Date":"27/06/2025"},{"Id":11347,"Name":"Ceinture d'Ougicle","CraftCost":7261,"RuneCost":0,"ResellPrice":7999,"Renta":738,"Date":"27/06/2025"},{"Id":18435,"Name":"Anneau d'El Piko","CraftCost":245785,"RuneCost":0,"ResellPrice":260999,"Renta":15214,"Date":"27/06/2025"},{"Id":11729,"Name":"Amulette Cætera","CraftCost":229250,"RuneCost":0,"ResellPrice":449699,"Renta":220449,"Date":"27/06/2025"},{"Id":6452,"Name":"Arc Chitecte","CraftCost":59623,"RuneCost":0,"ResellPrice":888999,"Renta":829376,"Date":"27/06/2025"},{"Id":6825,"Name":"Pantoufles Crochues du Chef Crocodaille","CraftCost":24627,"RuneCost":0,"ResellPrice":23999,"Renta":-628,"Date":"27/06/2025"},{"Id":8934,"Name":"Hache Harnée","CraftCost":116547,"RuneCost":0,"ResellPrice":129998,"Renta":13451,"Date":"27/06/2025"},{"Id":8295,"Name":"Arc du Dragoeuf","CraftCost":101121,"RuneCost":0,"ResellPrice":98887,"Renta":-2234,"Date":"27/06/2025"},{"Id":7243,"Name":"Geta Terrdala","CraftCost":33865,"RuneCost":0,"ResellPrice":43999,"Renta":10134,"Date":"27/06/2025"},{"Id":6983,"Name":"Dagues Réceuses","CraftCost":112815,"RuneCost":0,"ResellPrice":96999,"Renta":-15816,"Date":"27/06/2025"},{"Id":6536,"Name":"Pelle du Mineur Sombre","CraftCost":78065,"RuneCost":0,"ResellPrice":140999,"Renta":62934,"Date":"27/06/2025"},{"Id":6540,"Name":"La Pelle Hélabète","CraftCost":40229,"RuneCost":0,"ResellPrice":46999,"Renta":6770,"Date":"27/06/2025"},{"Id":6508,"Name":"Marteau Pinambour","CraftCost":9450,"RuneCost":0,"ResellPrice":52699,"Renta":43249,"Date":"27/06/2025"},{"Id":15200,"Name":"Cape Phossile","CraftCost":199936,"RuneCost":0,"ResellPrice":127999,"Renta":-71937,"Date":"27/06/2025"},{"Id":12675,"Name":"Collier Rouge de Daïgoro","CraftCost":55675,"RuneCost":0,"ResellPrice":114998,"Renta":59323,"Date":"27/06/2025"},{"Id":8825,"Name":"Masse du Corailleur Magistral","CraftCost":110436,"RuneCost":0,"ResellPrice":148999,"Renta":38563,"Date":"27/06/2025"},{"Id":14881,"Name":"Pikottes","CraftCost":852340,"RuneCost":0,"ResellPrice":789999,"Renta":-62341,"Date":"27/06/2025"},{"Id":12104,"Name":"Bague de Boréale","CraftCost":555149,"RuneCost":0,"ResellPrice":699998,"Renta":144849,"Date":"27/06/2025"},{"Id":11730,"Name":"Amulette Héroclite","CraftCost":581940,"RuneCost":0,"ResellPrice":299999,"Renta":-281941,"Date":"27/06/2025"},{"Id":8276,"Name":"Bottes du Minotoror","CraftCost":132496,"RuneCost":0,"ResellPrice":176999,"Renta":44503,"Date":"27/06/2025"},{"Id":9162,"Name":"Bloptes Griotte Royales","CraftCost":15768,"RuneCost":0,"ResellPrice":28998,"Renta":13230,"Date":"27/06/2025"},{"Id":8848,"Name":"Coiffe du Maître Zoth","CraftCost":124448,"RuneCost":0,"ResellPrice":149994,"Renta":25546,"Date":"27/06/2025"},{"Id":11605,"Name":"Cape Ricieuse","CraftCost":65872,"RuneCost":0,"ResellPrice":89989,"Renta":24117,"Date":"27/06/2025"},{"Id":9394,"Name":"Chapblopignon","CraftCost":110928,"RuneCost":0,"ResellPrice":89999,"Renta":-20929,"Date":"27/06/2025"},{"Id":6499,"Name":"Amulette \"Dents de Wabbits\"","CraftCost":4956,"RuneCost":0,"ResellPrice":10203,"Renta":5247,"Date":"27/06/2025"},{"Id":7211,"Name":"Hache du Yondanwa","CraftCost":24252,"RuneCost":0,"ResellPrice":79999,"Renta":55747,"Date":"27/06/2025"},{"Id":17593,"Name":"Bottes du Pounicheur","CraftCost":163597,"RuneCost":0,"ResellPrice":178499,"Renta":14902,"Date":"27/06/2025"},{"Id":14072,"Name":"Sangle de Sylargh","CraftCost":794695,"RuneCost":0,"ResellPrice":1399998,"Renta":605303,"Date":"27/06/2025"},{"Id":8092,"Name":"Les Dagues du Bouwin","CraftCost":60212,"RuneCost":0,"ResellPrice":183999,"Renta":123787,"Date":"27/06/2025"},{"Id":17587,"Name":"Col de Ush","CraftCost":426615,"RuneCost":0,"ResellPrice":699998,"Renta":273383,"Date":"27/06/2025"},{"Id":11611,"Name":"Slip Hie","CraftCost":285001,"RuneCost":0,"ResellPrice":289999,"Renta":4998,"Date":"27/06/2025"},{"Id":9165,"Name":"Bloptes Indigo Royales","CraftCost":15925,"RuneCost":0,"ResellPrice":101999,"Renta":86074,"Date":"27/06/2025"},{"Id":9170,"Name":"Blopture Indigo","CraftCost":10116,"RuneCost":0,"ResellPrice":24999,"Renta":14883,"Date":"27/06/2025"},{"Id":7553,"Name":"Chapodindo","CraftCost":4136,"RuneCost":0,"ResellPrice":6994,"Renta":2858,"Date":"27/06/2025"},{"Id":8614,"Name":"Pelle Ripe","CraftCost":19287,"RuneCost":0,"ResellPrice":23999,"Renta":4712,"Date":"27/06/2025"},{"Id":18588,"Name":"Capikténia","CraftCost":660081,"RuneCost":0,"ResellPrice":599999,"Renta":-60082,"Date":"27/06/2025"},{"Id":11577,"Name":"Anneau du Mansot Royal","CraftCost":154255,"RuneCost":0,"ResellPrice":109999,"Renta":-44256,"Date":"27/06/2025"},{"Id":11514,"Name":"Grésilosceptre","CraftCost":395904,"RuneCost":0,"ResellPrice":439999,"Renta":44095,"Date":"27/06/2025"},{"Id":11706,"Name":"Chapeau Tiche","CraftCost":466059,"RuneCost":0,"ResellPrice":639998,"Renta":173939,"Date":"27/06/2025"},{"Id":11625,"Name":"Hache Haimenu","CraftCost":169846,"RuneCost":0,"ResellPrice":183999,"Renta":14153,"Date":"27/06/2025"},{"Id":12854,"Name":"Porte-Malheur du Nowel Cauchemardesque","CraftCost":0,"RuneCost":0,"ResellPrice":691110,"Renta":691110,"Date":"27/06/2025"},{"Id":7165,"Name":"Baguette Nah","CraftCost":76189,"RuneCost":0,"ResellPrice":60599,"Renta":-15590,"Date":"27/06/2025"},{"Id":8846,"Name":"Chapeau de la Gamine Zoth","CraftCost":99967,"RuneCost":0,"ResellPrice":781999,"Renta":682032,"Date":"27/06/2025"},{"Id":14062,"Name":"Bottes de Missiz Frizz","CraftCost":895811,"RuneCost":0,"ResellPrice":1268989,"Renta":373178,"Date":"27/06/2025"},{"Id":14061,"Name":"Alliance de Missiz Frizz","CraftCost":1115828,"RuneCost":0,"ResellPrice":589998,"Renta":-525830,"Date":"27/06/2025"},{"Id":6767,"Name":"Bracelet Magique de Farle","CraftCost":33553,"RuneCost":0,"ResellPrice":39999,"Renta":6446,"Date":"27/06/2025"},{"Id":18423,"Name":"Cape Ouroboulos","CraftCost":34235,"RuneCost":0,"ResellPrice":33999,"Renta":-236,"Date":"27/06/2025"},{"Id":9124,"Name":"Blopanneau Coco","CraftCost":11633,"RuneCost":0,"ResellPrice":21999,"Renta":10366,"Date":"27/06/2025"},{"Id":13459,"Name":"Diplamu","CraftCost":4231,"RuneCost":0,"ResellPrice":18999,"Renta":14768,"Date":"27/06/2025"},{"Id":14498,"Name":"Amulette du Wabbit Céphale","CraftCost":313632,"RuneCost":0,"ResellPrice":239999,"Renta":-73633,"Date":"27/06/2025"},{"Id":7116,"Name":"Anneau Merta","CraftCost":6297,"RuneCost":0,"ResellPrice":9998,"Renta":3701,"Date":"27/06/2025"},{"Id":9156,"Name":"Amublop Indigo Royale","CraftCost":15209,"RuneCost":0,"ResellPrice":25999,"Renta":10790,"Date":"27/06/2025"},{"Id":6474,"Name":"Dragocoiffe Charbon","CraftCost":12588,"RuneCost":0,"ResellPrice":16399,"Renta":3811,"Date":"27/06/2025"},{"Id":11720,"Name":"Amulette du Glourséleste","CraftCost":754493,"RuneCost":0,"ResellPrice":899998,"Renta":145505,"Date":"27/06/2025"},{"Id":9147,"Name":"Chapignon","CraftCost":725043,"RuneCost":0,"ResellPrice":489999,"Renta":-235044,"Date":"27/06/2025"},{"Id":11763,"Name":"Pelle Fik","CraftCost":407298,"RuneCost":0,"ResellPrice":499999,"Renta":92701,"Date":"27/06/2025"},{"Id":7188,"Name":"Dagues Rhumes","CraftCost":57270,"RuneCost":0,"ResellPrice":129989,"Renta":72719,"Date":"27/06/2025"},{"Id":11627,"Name":"Arc Tangente","CraftCost":221919,"RuneCost":0,"ResellPrice":409999,"Renta":188080,"Date":"27/06/2025"},{"Id":2614,"Name":"Hache de Dame Oise","CraftCost":30391,"RuneCost":0,"ResellPrice":48999,"Renta":18608,"Date":"27/06/2025"},{"Id":14884,"Name":"Amulette Ikête","CraftCost":518735,"RuneCost":0,"ResellPrice":611239,"Renta":92504,"Date":"27/06/2025"},{"Id":6512,"Name":"Marteau Nitruhant","CraftCost":40692,"RuneCost":0,"ResellPrice":292999,"Renta":252307,"Date":"27/06/2025"},{"Id":8147,"Name":"Casque du Craqueleur Légendaire","CraftCost":357053,"RuneCost":0,"ResellPrice":19999,"Renta":-337054,"Date":"27/06/2025"},{"Id":15504,"Name":"Cape de Dremoan","CraftCost":803306,"RuneCost":0,"ResellPrice":989999,"Renta":186693,"Date":"27/06/2025"},{"Id":6523,"Name":"La Racine Hagogue","CraftCost":145902,"RuneCost":0,"ResellPrice":149998,"Renta":4096,"Date":"27/06/2025"},{"Id":348,"Name":"Bottes de Céleri-Thé","CraftCost":4396,"RuneCost":0,"ResellPrice":7999,"Renta":3603,"Date":"27/06/2025"},{"Id":15507,"Name":"Bottes du Capitaine Ekarlatte","CraftCost":259537,"RuneCost":0,"ResellPrice":289999,"Renta":30462,"Date":"27/06/2025"},{"Id":17590,"Name":"Cape des Matougarous","CraftCost":314131,"RuneCost":0,"ResellPrice":319999,"Renta":5868,"Date":"27/06/2025"},{"Id":8864,"Name":"Kask'Arc Go","CraftCost":117514,"RuneCost":0,"ResellPrice":231999,"Renta":114485,"Date":"27/06/2025"},{"Id":11609,"Name":"Talisman Doline","CraftCost":62966,"RuneCost":0,"ResellPrice":79999,"Renta":17033,"Date":"27/06/2025"},{"Id":14585,"Name":"Clef à Molette","CraftCost":89539,"RuneCost":0,"ResellPrice":412999,"Renta":323460,"Date":"27/06/2025"},{"Id":7192,"Name":"Griffe de Grizmine","CraftCost":68870,"RuneCost":0,"ResellPrice":373999,"Renta":305129,"Date":"27/06/2025"},{"Id":13128,"Name":"Ceinture de Léthaline","CraftCost":818576,"RuneCost":0,"ResellPrice":999999,"Renta":181423,"Date":"27/06/2025"},{"Id":18777,"Name":"Cape Tif","CraftCost":643889,"RuneCost":0,"ResellPrice":1129999,"Renta":486110,"Date":"27/06/2025"},{"Id":1499,"Name":"L'Enutrofion","CraftCost":6204,"RuneCost":0,"ResellPrice":623999,"Renta":617795,"Date":"27/06/2025"},{"Id":8149,"Name":"Craquanneau Légendaire","CraftCost":11597,"RuneCost":0,"ResellPrice":17999,"Renta":6402,"Date":"27/06/2025"},{"Id":9159,"Name":"Bloptes Reinette","CraftCost":8071,"RuneCost":0,"ResellPrice":6999,"Renta":-1072,"Date":"27/06/2025"},{"Id":9174,"Name":"Blopture Indigo Royale","CraftCost":17291,"RuneCost":0,"ResellPrice":139999,"Renta":122708,"Date":"27/06/2025"},{"Id":15791,"Name":"Cape Xélomorphe","CraftCost":259859,"RuneCost":0,"ResellPrice":474999,"Renta":215140,"Date":"27/06/2025"},{"Id":6776,"Name":"Farlature","CraftCost":42207,"RuneCost":0,"ResellPrice":759999,"Renta":717792,"Date":"27/06/2025"},{"Id":11626,"Name":"Hache du Fancrôme","CraftCost":141333,"RuneCost":0,"ResellPrice":222999,"Renta":81666,"Date":"27/06/2025"},{"Id":18432,"Name":"Cascterre","CraftCost":163594,"RuneCost":0,"ResellPrice":427999,"Renta":264405,"Date":"27/06/2025"},{"Id":13486,"Name":"Krosmaussures","CraftCost":36692,"RuneCost":0,"ResellPrice":94299,"Renta":57607,"Date":"27/06/2025"},{"Id":11760,"Name":"Hache Achinecride","CraftCost":198701,"RuneCost":0,"ResellPrice":210999,"Renta":12298,"Date":"27/06/2025"},{"Id":6503,"Name":"Marteau Polpoulette","CraftCost":10627,"RuneCost":0,"ResellPrice":26899,"Renta":16272,"Date":"27/06/2025"},{"Id":10847,"Name":"Bottes d'Hulkrap","CraftCost":16124,"RuneCost":0,"ResellPrice":999925,"Renta":983801,"Date":"27/06/2025"},{"Id":8330,"Name":"Coiffe du Draguaindrop","CraftCost":67689,"RuneCost":0,"ResellPrice":43099,"Renta":-24590,"Date":"27/06/2025"},{"Id":11728,"Name":"Cape Hiculteur","CraftCost":669098,"RuneCost":0,"ResellPrice":912999,"Renta":243901,"Date":"27/06/2025"},{"Id":8870,"Name":"Ceinture sombre en Abrakleur","CraftCost":126432,"RuneCost":0,"ResellPrice":159999,"Renta":33567,"Date":"27/06/2025"},{"Id":17100,"Name":"Bâton de Zatoïshwan","CraftCost":855485,"RuneCost":0,"ResellPrice":789998,"Renta":-65487,"Date":"27/06/2025"},{"Id":18779,"Name":"Amulette Hale","CraftCost":1230567,"RuneCost":0,"ResellPrice":1099999,"Renta":-130568,"Date":"27/06/2025"},{"Id":18776,"Name":"Chapeau du Comte Razof","CraftCost":1125350,"RuneCost":0,"ResellPrice":1399999,"Renta":274649,"Date":"27/06/2025"},{"Id":18427,"Name":"Coiffennex","CraftCost":44529,"RuneCost":0,"ResellPrice":229999,"Renta":185470,"Date":"27/06/2025"},{"Id":12033,"Name":"Anneau de Logram","CraftCost":10441,"RuneCost":0,"ResellPrice":399999,"Renta":389558,"Date":"27/06/2025"},{"Id":11713,"Name":"Amulette du Korriandre","CraftCost":266903,"RuneCost":0,"ResellPrice":257999,"Renta":-8904,"Date":"27/06/2025"},{"Id":7218,"Name":"Sandales Adin","CraftCost":29560,"RuneCost":0,"ResellPrice":59998,"Renta":30438,"Date":"27/06/2025"},{"Id":13850,"Name":"Masque du Frelon Noir","CraftCost":246354,"RuneCost":0,"ResellPrice":590999,"Renta":344645,"Date":"27/06/2025"},{"Id":11470,"Name":"Grésilanneau","CraftCost":764651,"RuneCost":0,"ResellPrice":1149999,"Renta":385348,"Date":"27/06/2025"},{"Id":14886,"Name":"Marteau des Anciens Steamers","CraftCost":204076,"RuneCost":0,"ResellPrice":499999,"Renta":295923,"Date":"27/06/2025"},{"Id":13194,"Name":"Chapeau Potin","CraftCost":251899,"RuneCost":0,"ResellPrice":349999,"Renta":98100,"Date":"27/06/2025"},{"Id":2381,"Name":"Cape Flotteuse","CraftCost":25882,"RuneCost":0,"ResellPrice":1399094,"Renta":1373212,"Date":"27/06/2025"},{"Id":8878,"Name":"Kidorteau","CraftCost":22877,"RuneCost":0,"ResellPrice":19995,"Renta":-2882,"Date":"27/06/2025"},{"Id":14075,"Name":"Amulette du Kanimate","CraftCost":612741,"RuneCost":0,"ResellPrice":1000999,"Renta":388258,"Date":"27/06/2025"},{"Id":14056,"Name":"Bottes Vicieuses","CraftCost":1011824,"RuneCost":0,"ResellPrice":948999,"Renta":-62825,"Date":"27/06/2025"},{"Id":1079,"Name":"Masse Aj Taye","CraftCost":6958,"RuneCost":0,"ResellPrice":9999,"Renta":3041,"Date":"27/06/2025"},{"Id":7201,"Name":"Sabre Nidanwa","CraftCost":10151,"RuneCost":0,"ResellPrice":23468,"Renta":13317,"Date":"27/06/2025"},{"Id":8091,"Name":"La Canne Bière","CraftCost":142518,"RuneCost":0,"ResellPrice":145949,"Renta":3431,"Date":"27/06/2025"},{"Id":14002,"Name":"Bottes d'Inferno","CraftCost":298665,"RuneCost":0,"ResellPrice":427998,"Renta":129333,"Date":"27/06/2025"},{"Id":1383,"Name":"Marteau Re'Thu","CraftCost":5748,"RuneCost":0,"ResellPrice":349999,"Renta":344251,"Date":"27/06/2025"},{"Id":8454,"Name":"Gant du Rat Blanc","CraftCost":149348,"RuneCost":0,"ResellPrice":736999,"Renta":587651,"Date":"27/06/2025"},{"Id":16209,"Name":"Alliance des Forestiers","CraftCost":48403,"RuneCost":0,"ResellPrice":97999,"Renta":49596,"Date":"27/06/2025"},{"Id":12414,"Name":"Sac de Voyage du Parfait Petit Vulkain","CraftCost":68840,"RuneCost":0,"ResellPrice":464999,"Renta":396159,"Date":"27/06/2025"},{"Id":11579,"Name":"Bague de l'Obsidiantre","CraftCost":434268,"RuneCost":0,"ResellPrice":619999,"Renta":185731,"Date":"27/06/2025"},{"Id":14008,"Name":"Mandrano","CraftCost":382984,"RuneCost":0,"ResellPrice":544999,"Renta":162015,"Date":"27/06/2025"},{"Id":7136,"Name":"Médaille Kido","CraftCost":114534,"RuneCost":0,"ResellPrice":249999,"Renta":135465,"Date":"27/06/2025"},{"Id":7002,"Name":"La Résinette","CraftCost":21682,"RuneCost":0,"ResellPrice":129999,"Renta":108317,"Date":"27/06/2025"},{"Id":12372,"Name":"Gantelet du Gorgouille","CraftCost":49122,"RuneCost":0,"ResellPrice":121999,"Renta":72877,"Date":"27/06/2025"},{"Id":9122,"Name":"Blopanneau Griotte","CraftCost":12801,"RuneCost":0,"ResellPrice":79999,"Renta":67198,"Date":"27/06/2025"},{"Id":8445,"Name":"Collier du Rat Noir","CraftCost":84971,"RuneCost":0,"ResellPrice":149998,"Renta":65027,"Date":"27/06/2025"},{"Id":7001,"Name":"Talisman du Faucheur d'Avoine","CraftCost":6960,"RuneCost":0,"ResellPrice":83499,"Renta":76539,"Date":"27/06/2025"},{"Id":7251,"Name":"Amulette Terrdala","CraftCost":33381,"RuneCost":0,"ResellPrice":84998,"Renta":51617,"Date":"27/06/2025"},{"Id":13460,"Name":"Diplanneau","CraftCost":15066,"RuneCost":0,"ResellPrice":55553,"Renta":40487,"Date":"27/06/2025"},{"Id":8004,"Name":"Anneau du Koalak","CraftCost":3710,"RuneCost":0,"ResellPrice":19999,"Renta":16289,"Date":"27/06/2025"},{"Id":15508,"Name":"Gant du Capitaine Ekarlatte","CraftCost":190655,"RuneCost":0,"ResellPrice":299999,"Renta":109344,"Date":"27/06/2025"},{"Id":8268,"Name":"Collier du Minotoror","CraftCost":204331,"RuneCost":0,"ResellPrice":299999,"Renta":95668,"Date":"27/06/2025"},{"Id":11622,"Name":"Anneau Nobstant","CraftCost":126492,"RuneCost":0,"ResellPrice":179999,"Renta":53507,"Date":"27/06/2025"},{"Id":9157,"Name":"Amublop Multicolore Royale","CraftCost":29945,"RuneCost":0,"ResellPrice":79999,"Renta":50054,"Date":"27/06/2025"},{"Id":7117,"Name":"Alliance Ethnique","CraftCost":7381,"RuneCost":0,"ResellPrice":44999,"Renta":37618,"Date":"27/06/2025"},{"Id":12085,"Name":"Anneau Moutheur","CraftCost":79466,"RuneCost":0,"ResellPrice":159999,"Renta":80533,"Date":"27/06/2025"},{"Id":15776,"Name":"Pantoufles de Soissanth","CraftCost":315392,"RuneCost":0,"ResellPrice":449999,"Renta":134607,"Date":"27/06/2025"},{"Id":8467,"Name":"Protège-Tibias Ancestraux","CraftCost":78273,"RuneCost":0,"ResellPrice":186999,"Renta":108726,"Date":"27/06/2025"},{"Id":11584,"Name":"Ceinture du Royalmouth","CraftCost":198575,"RuneCost":0,"ResellPrice":435999,"Renta":237424,"Date":"27/06/2025"},{"Id":8666,"Name":"Bottes Hairo","CraftCost":61605,"RuneCost":0,"ResellPrice":148996,"Renta":87391,"Date":"27/06/2025"},{"Id":2681,"Name":"Ceinture Tortue Jaune","CraftCost":15368,"RuneCost":0,"ResellPrice":71428,"Renta":56060,"Date":"27/06/2025"},{"Id":8651,"Name":"Sangle Hynère","CraftCost":65849,"RuneCost":0,"ResellPrice":119998,"Renta":54149,"Date":"27/06/2025"},{"Id":8665,"Name":"Bottes Hox","CraftCost":61525,"RuneCost":0,"ResellPrice":144999,"Renta":83474,"Date":"27/06/2025"},{"Id":8277,"Name":"Sandales du Minotot","CraftCost":218753,"RuneCost":0,"ResellPrice":299998,"Renta":81245,"Date":"27/06/2025"},{"Id":8471,"Name":"Tongues du dimanche du Chêne Mou","CraftCost":70411,"RuneCost":0,"ResellPrice":134999,"Renta":64588,"Date":"27/06/2025"},{"Id":11080,"Name":"Bottes de Lonne","CraftCost":10981,"RuneCost":0,"ResellPrice":66999,"Renta":56018,"Date":"27/06/2025"},{"Id":13137,"Name":"Ceinture de Coffreté","CraftCost":14918,"RuneCost":0,"ResellPrice":82289,"Renta":67371,"Date":"27/06/2025"},{"Id":8462,"Name":"Bottes Cérémoniales du Seigneur des Rats","CraftCost":55498,"RuneCost":0,"ResellPrice":109999,"Renta":54501,"Date":"27/06/2025"},{"Id":8668,"Name":"Bottes Hanik","CraftCost":63565,"RuneCost":0,"ResellPrice":145998,"Renta":82433,"Date":"27/06/2025"},{"Id":8283,"Name":"Ceinture du Minotot","CraftCost":222209,"RuneCost":0,"ResellPrice":298998,"Renta":76789,"Date":"27/06/2025"},{"Id":6831,"Name":"Ceinture du Chef Crocodaille","CraftCost":25794,"RuneCost":0,"ResellPrice":67499,"Renta":41705,"Date":"27/06/2025"},{"Id":8667,"Name":"Bottes Ulisme","CraftCost":65065,"RuneCost":0,"ResellPrice":144443,"Renta":79378,"Date":"27/06/2025"},{"Id":6745,"Name":"Ceinture Fourbissante","CraftCost":99703,"RuneCost":0,"ResellPrice":149998,"Renta":50295,"Date":"27/06/2025"},{"Id":8418,"Name":"Ceinture du Mominotor","CraftCost":149675,"RuneCost":0,"ResellPrice":374099,"Renta":224424,"Date":"27/06/2025"},{"Id":8713,"Name":"Geta Bernacle","CraftCost":64905,"RuneCost":0,"ResellPrice":139999,"Renta":75094,"Date":"27/06/2025"},{"Id":11581,"Name":"Cape de l'Obsidiantre","CraftCost":191177,"RuneCost":0,"ResellPrice":344989,"Renta":153812,"Date":"27/06/2025"},{"Id":8820,"Name":"Masque du Sergent Zoth","CraftCost":139846,"RuneCost":0,"ResellPrice":259997,"Renta":120151,"Date":"27/06/2025"},{"Id":18434,"Name":"Sombrero d'El Piko","CraftCost":275058,"RuneCost":0,"ResellPrice":394999,"Renta":119941,"Date":"27/06/2025"},{"Id":11718,"Name":"Masque du Glourséleste","CraftCost":337320,"RuneCost":0,"ResellPrice":449998,"Renta":112678,"Date":"27/06/2025"},{"Id":14583,"Name":"Scaramouchapeau","CraftCost":97875,"RuneCost":0,"ResellPrice":189998,"Renta":92123,"Date":"27/06/2025"},{"Id":8639,"Name":"Cape Aurale","CraftCost":27885,"RuneCost":0,"ResellPrice":89999,"Renta":62114,"Date":"27/06/2025"},{"Id":12856,"Name":"Sacoche de Redolphe","CraftCost":128974,"RuneCost":0,"ResellPrice":256999,"Renta":128025,"Date":"27/06/2025"},{"Id":6994,"Name":"Cape Hôte","CraftCost":3751,"RuneCost":0,"ResellPrice":49998,"Renta":46247,"Date":"27/06/2025"},{"Id":971,"Name":"Cape du Wa Wabbit","CraftCost":14330,"RuneCost":0,"ResellPrice":93599,"Renta":79269,"Date":"27/06/2025"},{"Id":7142,"Name":"Piruk","CraftCost":135826,"RuneCost":0,"ResellPrice":239999,"Renta":104173,"Date":"27/06/2025"},{"Id":6481,"Name":"Dora Bora","CraftCost":226168,"RuneCost":0,"ResellPrice":239999,"Renta":13831,"Date":"27/06/2025"},{"Id":8443,"Name":"Cape du Rat Noir","CraftCost":72466,"RuneCost":0,"ResellPrice":134998,"Renta":62532,"Date":"27/06/2025"},{"Id":8647,"Name":"Cape Wéra","CraftCost":26565,"RuneCost":0,"ResellPrice":84996,"Renta":58431,"Date":"27/06/2025"},{"Id":8304,"Name":"Shikacoiffe","CraftCost":55137,"RuneCost":0,"ResellPrice":137799,"Renta":82662,"Date":"27/06/2025"},{"Id":17595,"Name":"Scalp du Pounicheur","CraftCost":139103,"RuneCost":0,"ResellPrice":198999,"Renta":59896,"Date":"27/06/2025"},{"Id":2489,"Name":"Vegacape","CraftCost":9219,"RuneCost":0,"ResellPrice":100000,"Renta":90781,"Date":"27/06/2025"},{"Id":14519,"Name":"Marteau du Juge Lou","CraftCost":317053,"RuneCost":0,"ResellPrice":459999,"Renta":142946,"Date":"27/06/2025"},{"Id":11629,"Name":"Youyettes","CraftCost":380561,"RuneCost":0,"ResellPrice":549997,"Renta":169436,"Date":"27/06/2025"},{"Id":7255,"Name":"Hache Terrdala","CraftCost":32377,"RuneCost":0,"ResellPrice":144442,"Renta":112065,"Date":"27/06/2025"},{"Id":8100,"Name":"La Hache Ticot","CraftCost":21222,"RuneCost":0,"ResellPrice":119999,"Renta":98777,"Date":"27/06/2025"},{"Id":11624,"Name":"Sabre Heutelle","CraftCost":230595,"RuneCost":0,"ResellPrice":324999,"Renta":94404,"Date":"27/06/2025"},{"Id":7190,"Name":"Dagues Maydhyn China","CraftCost":33983,"RuneCost":0,"ResellPrice":109996,"Renta":76013,"Date":"27/06/2025"},{"Id":8599,"Name":"Griffettes","CraftCost":17884,"RuneCost":0,"ResellPrice":100000,"Renta":82116,"Date":"27/06/2025"},{"Id":11745,"Name":"Marteau Racle","CraftCost":173929,"RuneCost":0,"ResellPrice":308999,"Renta":135070,"Date":"27/06/2025"},{"Id":2544,"Name":"Corbalame","CraftCost":52864,"RuneCost":0,"ResellPrice":139999,"Renta":87135,"Date":"27/06/2025"},{"Id":8827,"Name":"Hache du Guerrier Zoth","CraftCost":114324,"RuneCost":0,"ResellPrice":193799,"Renta":79475,"Date":"27/06/2025"},{"Id":8274,"Name":"Hache du Minotoror","CraftCost":129822,"RuneCost":0,"ResellPrice":199999,"Renta":70177,"Date":"27/06/2025"},{"Id":202,"Name":"Razielle","CraftCost":7589,"RuneCost":0,"ResellPrice":49998,"Renta":42409,"Date":"27/06/2025"},{"Id":8413,"Name":"Marteau du Mominotor","CraftCost":206134,"RuneCost":0,"ResellPrice":289998,"Renta":83864,"Date":"27/06/2025"},{"Id":8936,"Name":"Pelle Shattkitou","CraftCost":91698,"RuneCost":0,"ResellPrice":197999,"Renta":106301,"Date":"27/06/2025"},{"Id":18437,"Name":"Dagues Cacterre","CraftCost":127762,"RuneCost":0,"ResellPrice":189998,"Renta":62236,"Date":"27/06/2025"},{"Id":2603,"Name":"Trancheuse de Partie","CraftCost":13093,"RuneCost":0,"ResellPrice":54949,"Renta":41856,"Date":"27/06/2025"},{"Id":8419,"Name":"Pelle Moh","CraftCost":55890,"RuneCost":0,"ResellPrice":99997,"Renta":44107,"Date":"27/06/2025"},{"Id":8089,"Name":"Baguette Iots","CraftCost":81503,"RuneCost":0,"ResellPrice":158499,"Renta":76996,"Date":"27/06/2025"},{"Id":17460,"Name":"Baguette Osseuse","CraftCost":16808,"RuneCost":0,"ResellPrice":79989,"Renta":63181,"Date":"27/06/2025"},{"Id":6451,"Name":"Arc Ange","CraftCost":41982,"RuneCost":0,"ResellPrice":95199,"Renta":53217,"Date":"27/06/2025"},{"Id":8005,"Name":"Arc du Koalak","CraftCost":14134,"RuneCost":0,"ResellPrice":79999,"Renta":65865,"Date":"27/06/2025"},{"Id":8608,"Name":"La Bastonneuze","CraftCost":20050,"RuneCost":0,"ResellPrice":64849,"Renta":44799,"Date":"27/06/2025"},{"Id":7169,"Name":"Baguette Hincelle","CraftCost":80978,"RuneCost":0,"ResellPrice":129994,"Renta":49016,"Date":"27/06/2025"},{"Id":1162,"Name":"Bâton des Rois","CraftCost":18738,"RuneCost":0,"ResellPrice":59998,"Renta":41260,"Date":"27/06/2025"},{"Id":1331,"Name":"Médaille Oly","CraftCost":5005,"RuneCost":0,"ResellPrice":1260049,"Renta":1255044,"Date":"28/06/2025"},{"Id":6500,"Name":"Oreilles de Wabbits","CraftCost":11642,"RuneCost":0,"ResellPrice":61223,"Renta":49581,"Date":"28/06/2025"},{"Id":180,"Name":"La Baguette des Limbes","CraftCost":152144,"RuneCost":0,"ResellPrice":105999,"Renta":-46145,"Date":"28/06/2025"},{"Id":5122,"Name":"La Maîtrise des Poupées","CraftCost":22827,"RuneCost":0,"ResellPrice":49999,"Renta":27172,"Date":"28/06/2025"},{"Id":6468,"Name":"Anneau du Jeune Vald","CraftCost":12969,"RuneCost":0,"ResellPrice":38499,"Renta":25530,"Date":"28/06/2025"},{"Id":6465,"Name":"Anneau de Loopine","CraftCost":19944,"RuneCost":0,"ResellPrice":100000,"Renta":80056,"Date":"28/06/2025"},{"Id":6506,"Name":"Anneau du Mineur Gogorifiant","CraftCost":48983,"RuneCost":0,"ResellPrice":67999,"Renta":19016,"Date":"28/06/2025"},{"Id":1668,"Name":"Ceinture du Dodu Trembleur","CraftCost":4920,"RuneCost":0,"ResellPrice":599999,"Renta":595079,"Date":"28/06/2025"},{"Id":127,"Name":"Bottes de Bowisse","CraftCost":7108,"RuneCost":0,"ResellPrice":34998,"Renta":27890,"Date":"28/06/2025"},{"Id":1665,"Name":"Bottes d'Apprentissage","CraftCost":16477,"RuneCost":0,"ResellPrice":42998,"Renta":26521,"Date":"28/06/2025"},{"Id":2685,"Name":"Ceinture Tortue Verte","CraftCost":16426,"RuneCost":0,"ResellPrice":41999,"Renta":25573,"Date":"28/06/2025"},{"Id":2369,"Name":"Puissante Ceinture Fulgurante","CraftCost":26205,"RuneCost":0,"ResellPrice":49887,"Renta":23682,"Date":"28/06/2025"},{"Id":968,"Name":"Ceinture Fulgurante","CraftCost":13782,"RuneCost":0,"ResellPrice":68749,"Renta":54967,"Date":"28/06/2025"},{"Id":2373,"Name":"Moon Boutse","CraftCost":20348,"RuneCost":0,"ResellPrice":60999,"Renta":40651,"Date":"28/06/2025"},{"Id":2687,"Name":"Ceinture Tortue Rouge","CraftCost":16880,"RuneCost":0,"ResellPrice":37399,"Renta":20519,"Date":"28/06/2025"},{"Id":2489,"Name":"Vegacape","CraftCost":8455,"RuneCost":0,"ResellPrice":999999,"Renta":991544,"Date":"28/06/2025"},{"Id":6481,"Name":"Dora Bora","CraftCost":226168,"RuneCost":0,"ResellPrice":305999,"Renta":79831,"Date":"28/06/2025"},{"Id":2532,"Name":"Caracape","CraftCost":9282,"RuneCost":0,"ResellPrice":40815,"Renta":31533,"Date":"28/06/2025"},{"Id":967,"Name":"Cape Fulgurante","CraftCost":13090,"RuneCost":0,"ResellPrice":23999,"Renta":10909,"Date":"28/06/2025"},{"Id":969,"Name":"Couronne du Wa Wabbit","CraftCost":14090,"RuneCost":0,"ResellPrice":39999,"Renta":25909,"Date":"28/06/2025"},{"Id":2094,"Name":"Makroute Sombre","CraftCost":17190,"RuneCost":0,"ResellPrice":29999,"Renta":12809,"Date":"28/06/2025"},{"Id":1910,"Name":"Cape Ouginak","CraftCost":8657,"RuneCost":0,"ResellPrice":18999,"Renta":10342,"Date":"28/06/2025"},{"Id":233,"Name":"Kaiser","CraftCost":81187,"RuneCost":0,"ResellPrice":222221,"Renta":141034,"Date":"28/06/2025"},{"Id":6505,"Name":"Marteau Réhadaure","CraftCost":44986,"RuneCost":0,"ResellPrice":183672,"Renta":138686,"Date":"28/06/2025"},{"Id":1511,"Name":"Neuf Queues","CraftCost":29698,"RuneCost":0,"ResellPrice":63999,"Renta":34301,"Date":"28/06/2025"},{"Id":1040,"Name":"Lames sanglantes d'Ortimus Contrari","CraftCost":15279,"RuneCost":0,"ResellPrice":45199,"Renta":29920,"Date":"28/06/2025"},{"Id":1427,"Name":"Pelle Zébuth","CraftCost":7824,"RuneCost":0,"ResellPrice":28999,"Renta":21175,"Date":"28/06/2025"},{"Id":1085,"Name":"Marteau des Falistos","CraftCost":11411,"RuneCost":0,"ResellPrice":29998,"Renta":18587,"Date":"28/06/2025"},{"Id":1436,"Name":"Pelle Ikan","CraftCost":7569,"RuneCost":0,"ResellPrice":19997,"Renta":12428,"Date":"28/06/2025"},{"Id":1431,"Name":"Pelle Mechba","CraftCost":2798,"RuneCost":0,"ResellPrice":14499,"Renta":11701,"Date":"28/06/2025"},{"Id":6511,"Name":"Marteau Ridhe","CraftCost":45471,"RuneCost":0,"ResellPrice":69998,"Renta":24527,"Date":"28/06/2025"},{"Id":3647,"Name":"La Thor-Boyaux","CraftCost":25090,"RuneCost":0,"ResellPrice":75899,"Renta":50809,"Date":"28/06/2025"},{"Id":1035,"Name":"Lame de Fon","CraftCost":4693,"RuneCost":0,"ResellPrice":15999,"Renta":11306,"Date":"28/06/2025"},{"Id":6453,"Name":"Arc du Pêcheur","CraftCost":15943,"RuneCost":0,"ResellPrice":399999,"Renta":384056,"Date":"28/06/2025"},{"Id":1132,"Name":"Baguette Ni'Ninnin","CraftCost":26467,"RuneCost":0,"ResellPrice":63649,"Renta":37182,"Date":"28/06/2025"},{"Id":6494,"Name":"Baguette d'Elya Wood","CraftCost":47784,"RuneCost":0,"ResellPrice":77498,"Renta":29714,"Date":"28/06/2025"},{"Id":5999,"Name":"Baguette Helles","CraftCost":19411,"RuneCost":0,"ResellPrice":48999,"Renta":29588,"Date":"28/06/2025"},{"Id":1146,"Name":"Baguette Meneuse","CraftCost":10861,"RuneCost":0,"ResellPrice":34995,"Renta":24134,"Date":"28/06/2025"},{"Id":1739,"Name":"Baguette Affeulante","CraftCost":25281,"RuneCost":0,"ResellPrice":100000,"Renta":74719,"Date":"28/06/2025"},{"Id":970,"Name":"Bâton du Wa Wabbit","CraftCost":9451,"RuneCost":0,"ResellPrice":27999,"Renta":18548,"Date":"28/06/2025"},{"Id":6491,"Name":"Le Tronknydum","CraftCost":7194,"RuneCost":0,"ResellPrice":24999,"Renta":17805,"Date":"28/06/2025"},{"Id":6497,"Name":"Balgourde des Clairettes","CraftCost":13393,"RuneCost":0,"ResellPrice":39998,"Renta":26605,"Date":"28/06/2025"},{"Id":6522,"Name":"La Racine Cinati","CraftCost":57215,"RuneCost":0,"ResellPrice":74998,"Renta":17783,"Date":"28/06/2025"},{"Id":6484,"Name":"Arc du Sram Archer","CraftCost":20891,"RuneCost":0,"ResellPrice":74699,"Renta":53808,"Date":"28/06/2025"},{"Id":333,"Name":"Baguette Deuh-Pain","CraftCost":13719,"RuneCost":0,"ResellPrice":32599,"Renta":18880,"Date":"28/06/2025"},{"Id":1131,"Name":"Baguette d'Eglise","CraftCost":4702,"RuneCost":0,"ResellPrice":14999,"Renta":10297,"Date":"28/06/2025"},{"Id":657,"Name":"Bâton du Maître des Tofus","CraftCost":7717,"RuneCost":0,"ResellPrice":46129,"Renta":38412,"Date":"28/06/2025"},{"Id":1140,"Name":"Baguette d'Houvette","CraftCost":8826,"RuneCost":0,"ResellPrice":19999,"Renta":11173,"Date":"28/06/2025"},{"Id":6496,"Name":"Baguette en Racine d'Abraknyde Sombre","CraftCost":13243,"RuneCost":0,"ResellPrice":23999,"Renta":10756,"Date":"28/06/2025"},{"Id":15518,"Name":"Amulette d'Ali Grothor","CraftCost":590593,"RuneCost":0,"ResellPrice":1799998,"Renta":1209405,"Date":"28/06/2025"},{"Id":11737,"Name":"Bracelet Ming","CraftCost":294919,"RuneCost":0,"ResellPrice":798999,"Renta":504080,"Date":"28/06/2025"},{"Id":12095,"Name":"Amulette de Cantile","CraftCost":180752,"RuneCost":0,"ResellPrice":484999,"Renta":304247,"Date":"28/06/2025"},{"Id":8411,"Name":"Pendentif du Mominotor","CraftCost":223871,"RuneCost":0,"ResellPrice":414999,"Renta":191128,"Date":"28/06/2025"},{"Id":8860,"Name":"Alliance de Corail","CraftCost":4867,"RuneCost":0,"ResellPrice":9999,"Renta":5132,"Date":"28/06/2025"},{"Id":13891,"Name":"Glaglano","CraftCost":6487,"RuneCost":0,"ResellPrice":994999,"Renta":988512,"Date":"28/06/2025"},{"Id":11738,"Name":"Anneau Aimgéroks","CraftCost":306400,"RuneCost":0,"ResellPrice":612479,"Renta":306079,"Date":"28/06/2025"},{"Id":13636,"Name":"Amulette de Nevark","CraftCost":722413,"RuneCost":0,"ResellPrice":1188999,"Renta":466586,"Date":"28/06/2025"},{"Id":15783,"Name":"Anneau de Fraktale","CraftCost":268792,"RuneCost":0,"ResellPrice":549998,"Renta":281206,"Date":"28/06/2025"},{"Id":11735,"Name":"Alliance Hestrale","CraftCost":286462,"RuneCost":0,"ResellPrice":499998,"Renta":213536,"Date":"28/06/2025"},{"Id":12969,"Name":"Bracelet du Minotoboule","CraftCost":421001,"RuneCost":0,"ResellPrice":828999,"Renta":407998,"Date":"28/06/2025"},{"Id":14058,"Name":"Anneau Glacial","CraftCost":720598,"RuneCost":0,"ResellPrice":948999,"Renta":228401,"Date":"28/06/2025"},{"Id":11714,"Name":"Anneau du Korriandre","CraftCost":272826,"RuneCost":0,"ResellPrice":479999,"Renta":207173,"Date":"28/06/2025"},{"Id":18778,"Name":"Chaussures Face","CraftCost":1482566,"RuneCost":0,"ResellPrice":2378999,"Renta":896433,"Date":"28/06/2025"},{"Id":17588,"Name":"Bottes de Ush","CraftCost":844637,"RuneCost":0,"ResellPrice":1263999,"Renta":419362,"Date":"28/06/2025"},{"Id":18433,"Name":"Cacture","CraftCost":155808,"RuneCost":0,"ResellPrice":428999,"Renta":273191,"Date":"28/06/2025"},{"Id":8861,"Name":"Sandales Circulaires du Kimbo","CraftCost":552629,"RuneCost":0,"ResellPrice":829998,"Renta":277369,"Date":"28/06/2025"},{"Id":13020,"Name":"Sabots Aiguilles de Féline","CraftCost":23793,"RuneCost":0,"ResellPrice":299999,"Renta":276206,"Date":"28/06/2025"},{"Id":8303,"Name":"Shikature","CraftCost":52991,"RuneCost":0,"ResellPrice":109999,"Renta":57008,"Date":"28/06/2025"},{"Id":9166,"Name":"Bloptes Multicolores Royales","CraftCost":29092,"RuneCost":0,"ResellPrice":232539,"Renta":203447,"Date":"28/06/2025"},{"Id":13132,"Name":"Ceinture d'Ogivol","CraftCost":1196057,"RuneCost":0,"ResellPrice":1976999,"Renta":780942,"Date":"28/06/2025"},{"Id":11721,"Name":"Ceinture du Glourséleste","CraftCost":326134,"RuneCost":0,"ResellPrice":799998,"Renta":473864,"Date":"28/06/2025"},{"Id":15762,"Name":"Bottes de XLII","CraftCost":449911,"RuneCost":0,"ResellPrice":759998,"Renta":310087,"Date":"28/06/2025"},{"Id":8415,"Name":"Bottes du Mominotor","CraftCost":133584,"RuneCost":0,"ResellPrice":380999,"Renta":247415,"Date":"28/06/2025"},{"Id":17119,"Name":"Ceinture du K.O.","CraftCost":1017912,"RuneCost":0,"ResellPrice":1199999,"Renta":182087,"Date":"28/06/2025"},{"Id":15198,"Name":"Bottes Phossiles","CraftCost":182397,"RuneCost":0,"ResellPrice":344999,"Renta":162602,"Date":"28/06/2025"},{"Id":11709,"Name":"Ceinture du Tengu Givrefoux","CraftCost":525047,"RuneCost":0,"ResellPrice":799999,"Renta":274952,"Date":"28/06/2025"},{"Id":9139,"Name":"Bottines des sous-bois","CraftCost":335876,"RuneCost":0,"ResellPrice":491999,"Renta":156123,"Date":"28/06/2025"},{"Id":14070,"Name":"Capuche de Sylargh","CraftCost":457889,"RuneCost":0,"ResellPrice":1249999,"Renta":792110,"Date":"28/06/2025"},{"Id":11472,"Name":"Grésilocape","CraftCost":989298,"RuneCost":0,"ResellPrice":1599999,"Renta":610701,"Date":"28/06/2025"},{"Id":8441,"Name":"Billréole","CraftCost":62873,"RuneCost":0,"ResellPrice":379996,"Renta":317123,"Date":"28/06/2025"},{"Id":11599,"Name":"Coiffe du Fricochère","CraftCost":163283,"RuneCost":0,"ResellPrice":449999,"Renta":286716,"Date":"28/06/2025"},{"Id":15062,"Name":"Coiffe de l'Orfélin","CraftCost":353383,"RuneCost":0,"ResellPrice":597999,"Renta":244616,"Date":"28/06/2025"},{"Id":8453,"Name":"Collier du Rat Blanc","CraftCost":74368,"RuneCost":0,"ResellPrice":98997,"Renta":24629,"Date":"28/06/2025"},{"Id":8414,"Name":"Dagues du Dragoeuf","CraftCost":207065,"RuneCost":0,"ResellPrice":239999,"Renta":32934,"Date":"28/06/2025"},{"Id":8268,"Name":"Collier du Minotoror","CraftCost":204331,"RuneCost":0,"ResellPrice":299998,"Renta":95667,"Date":"28/06/2025"},{"Id":8445,"Name":"Collier du Rat Noir","CraftCost":85123,"RuneCost":0,"ResellPrice":139999,"Renta":54876,"Date":"28/06/2025"},{"Id":11622,"Name":"Anneau Nobstant","CraftCost":126492,"RuneCost":0,"ResellPrice":179998,"Renta":53506,"Date":"28/06/2025"},{"Id":9125,"Name":"Blopanneau Indigo","CraftCost":8279,"RuneCost":0,"ResellPrice":49899,"Renta":41620,"Date":"28/06/2025"},{"Id":7117,"Name":"Alliance Ethnique","CraftCost":8455,"RuneCost":0,"ResellPrice":44999,"Renta":36544,"Date":"28/06/2025"},{"Id":8880,"Name":"Amufafah","CraftCost":58779,"RuneCost":0,"ResellPrice":94999,"Renta":36220,"Date":"28/06/2025"},{"Id":10852,"Name":"Amulette d'Hulkrap","CraftCost":14616,"RuneCost":0,"ResellPrice":49999,"Renta":35383,"Date":"28/06/2025"},{"Id":13138,"Name":"Pendentiffre","CraftCost":14763,"RuneCost":0,"ResellPrice":49799,"Renta":35036,"Date":"28/06/2025"},{"Id":14271,"Name":"Dés de la Chance","CraftCost":31357,"RuneCost":0,"ResellPrice":57999,"Renta":26642,"Date":"28/06/2025"},{"Id":11575,"Name":"Amulette du Royalmouth","CraftCost":90280,"RuneCost":0,"ResellPrice":224999,"Renta":134719,"Date":"28/06/2025"},{"Id":19089,"Name":"Anneau Riktus","CraftCost":27984,"RuneCost":0,"ResellPrice":57498,"Renta":29514,"Date":"28/06/2025"},{"Id":7880,"Name":"Amulette du Boufcoul","CraftCost":20529,"RuneCost":0,"ResellPrice":47996,"Renta":27467,"Date":"28/06/2025"},{"Id":8658,"Name":"Ceinture Bodiézèle","CraftCost":62129,"RuneCost":0,"ResellPrice":419999,"Renta":357870,"Date":"28/06/2025"},{"Id":11583,"Name":"Bottes de l'Obsidiantre","CraftCost":560963,"RuneCost":0,"ResellPrice":788887,"Renta":227924,"Date":"28/06/2025"},{"Id":8727,"Name":"Bottes Antouche","CraftCost":62291,"RuneCost":0,"ResellPrice":239999,"Renta":177708,"Date":"28/06/2025"},{"Id":7513,"Name":"Sandales Titude","CraftCost":176462,"RuneCost":0,"ResellPrice":274999,"Renta":98537,"Date":"28/06/2025"},{"Id":8468,"Name":"Abrature Ancestrale","CraftCost":60539,"RuneCost":0,"ResellPrice":99998,"Renta":39459,"Date":"28/06/2025"},{"Id":6468,"Name":"Anneau du Jeune Vald","CraftCost":13631,"RuneCost":0,"ResellPrice":38499,"Renta":24868,"Date":"28/06/2025"},{"Id":10853,"Name":"Amulette de Kloug","CraftCost":17846,"RuneCost":0,"ResellPrice":40815,"Renta":22969,"Date":"28/06/2025"},{"Id":9153,"Name":"Amublop Griotte Royale","CraftCost":15070,"RuneCost":0,"ResellPrice":36799,"Renta":21729,"Date":"28/06/2025"},{"Id":14304,"Name":"Amulette Stroplante","CraftCost":11940,"RuneCost":0,"ResellPrice":28998,"Renta":17058,"Date":"28/06/2025"},{"Id":7555,"Name":"Anodindo","CraftCost":3476,"RuneCost":0,"ResellPrice":19999,"Renta":16523,"Date":"28/06/2025"},{"Id":14311,"Name":"Justanneau","CraftCost":8882,"RuneCost":0,"ResellPrice":22999,"Renta":14117,"Date":"28/06/2025"},{"Id":11379,"Name":"Plumamulette","CraftCost":7604,"RuneCost":0,"ResellPrice":65589,"Renta":57985,"Date":"28/06/2025"},{"Id":9155,"Name":"Amublop Coco Royale","CraftCost":11818,"RuneCost":0,"ResellPrice":26089,"Renta":14271,"Date":"28/06/2025"},{"Id":11384,"Name":"Anoppinz","CraftCost":7558,"RuneCost":0,"ResellPrice":19999,"Renta":12441,"Date":"28/06/2025"},{"Id":11374,"Name":"Amupapier","CraftCost":9755,"RuneCost":0,"ResellPrice":21999,"Renta":12244,"Date":"28/06/2025"},{"Id":9156,"Name":"Amublop Indigo Royale","CraftCost":15395,"RuneCost":0,"ResellPrice":27999,"Renta":12604,"Date":"28/06/2025"},{"Id":7881,"Name":"Anneau du Boufcoul","CraftCost":16497,"RuneCost":0,"ResellPrice":26995,"Renta":10498,"Date":"28/06/2025"},{"Id":13485,"Name":"Krosmangle","CraftCost":47818,"RuneCost":0,"ResellPrice":79999,"Renta":32181,"Date":"28/06/2025"},{"Id":11375,"Name":"Slipapier","CraftCost":15808,"RuneCost":0,"ResellPrice":100000,"Renta":84192,"Date":"28/06/2025"},{"Id":7219,"Name":"Sandales Ailuya","CraftCost":14772,"RuneCost":0,"ResellPrice":100000,"Renta":85228,"Date":"28/06/2025"},{"Id":9170,"Name":"Blopture Indigo","CraftCost":10129,"RuneCost":0,"ResellPrice":23999,"Renta":13870,"Date":"28/06/2025"},{"Id":7885,"Name":"Ceinture du Boufcoul","CraftCost":36730,"RuneCost":0,"ResellPrice":100000,"Renta":63270,"Date":"28/06/2025"},{"Id":13582,"Name":"Ballerines Roses","CraftCost":8697,"RuneCost":0,"ResellPrice":22299,"Renta":13602,"Date":"28/06/2025"},{"Id":8119,"Name":"Scarature Dorée","CraftCost":10910,"RuneCost":0,"ResellPrice":22599,"Renta":11689,"Date":"28/06/2025"},{"Id":8455,"Name":"Ceinture du Rat Blanc","CraftCost":57084,"RuneCost":0,"ResellPrice":74998,"Renta":17914,"Date":"28/06/2025"},{"Id":9161,"Name":"Bloptes Indigo","CraftCost":3134,"RuneCost":0,"ResellPrice":38299,"Renta":35165,"Date":"28/06/2025"},{"Id":7240,"Name":"Ceinture Feudala","CraftCost":32037,"RuneCost":0,"ResellPrice":44999,"Renta":12962,"Date":"28/06/2025"},{"Id":11396,"Name":"Ceintusonnier","CraftCost":6731,"RuneCost":0,"ResellPrice":18699,"Renta":11968,"Date":"28/06/2025"},{"Id":9160,"Name":"Bloptes Coco","CraftCost":5868,"RuneCost":0,"ResellPrice":18999,"Renta":13131,"Date":"28/06/2025"},{"Id":6952,"Name":"Coiffe du Mulou","CraftCost":16684,"RuneCost":0,"ResellPrice":39799,"Renta":23115,"Date":"28/06/2025"},{"Id":8442,"Name":"Masque du Rat Noir","CraftCost":49935,"RuneCost":0,"ResellPrice":68999,"Renta":19064,"Date":"28/06/2025"},{"Id":7888,"Name":"Sac du Koulosse","CraftCost":22973,"RuneCost":0,"ResellPrice":38999,"Renta":16026,"Date":"28/06/2025"},{"Id":6830,"Name":"Petit sac d'écolier du Chef Crocodaille","CraftCost":15328,"RuneCost":0,"ResellPrice":29999,"Renta":14671,"Date":"28/06/2025"},{"Id":7339,"Name":"Coiffe du Kitsou","CraftCost":10996,"RuneCost":0,"ResellPrice":100000,"Renta":89004,"Date":"28/06/2025"},{"Id":18617,"Name":"Cape Hoile","CraftCost":37168,"RuneCost":0,"ResellPrice":49999,"Renta":12831,"Date":"28/06/2025"},{"Id":6930,"Name":"Casque du Craqueleur","CraftCost":7845,"RuneCost":0,"ResellPrice":18199,"Renta":10354,"Date":"28/06/2025"},{"Id":7229,"Name":"Chapeau Aerdala","CraftCost":11971,"RuneCost":0,"ResellPrice":34899,"Renta":22928,"Date":"28/06/2025"},{"Id":233,"Name":"Kaiser","CraftCost":75691,"RuneCost":0,"ResellPrice":222221,"Renta":146530,"Date":"28/06/2025"},{"Id":7256,"Name":"Dagues Aerdala","CraftCost":14557,"RuneCost":0,"ResellPrice":38998,"Renta":24441,"Date":"28/06/2025"},{"Id":7257,"Name":"Sabre Feudala","CraftCost":34130,"RuneCost":0,"ResellPrice":100000,"Renta":65870,"Date":"28/06/2025"},{"Id":18429,"Name":"Hache du Mantiscore","CraftCost":29156,"RuneCost":0,"ResellPrice":48999,"Renta":19843,"Date":"28/06/2025"},{"Id":8130,"Name":"Hache du Mulou","CraftCost":15344,"RuneCost":0,"ResellPrice":97899,"Renta":82555,"Date":"28/06/2025"},{"Id":6539,"Name":"Pelle Gicque","CraftCost":17015,"RuneCost":0,"ResellPrice":37399,"Renta":20384,"Date":"28/06/2025"},{"Id":7156,"Name":"Marteau Ronto","CraftCost":34224,"RuneCost":0,"ResellPrice":58993,"Renta":24769,"Date":"28/06/2025"},{"Id":970,"Name":"Bâton du Wa Wabbit","CraftCost":9837,"RuneCost":0,"ResellPrice":29699,"Renta":19862,"Date":"28/06/2025"},{"Id":8610,"Name":"Le Kikoularc","CraftCost":9103,"RuneCost":0,"ResellPrice":26998,"Renta":17895,"Date":"28/06/2025"},{"Id":6525,"Name":"Bâton du Féca","CraftCost":19984,"RuneCost":0,"ResellPrice":34849,"Renta":14865,"Date":"28/06/2025"},{"Id":7206,"Name":"Bâton du Sandanwa","CraftCost":27109,"RuneCost":0,"ResellPrice":39996,"Renta":12887,"Date":"28/06/2025"},{"Id":1665,"Name":"Bottes d'Apprentissage","CraftCost":16717,"RuneCost":0,"ResellPrice":38999,"Renta":22282,"Date":"29/06/2025"},{"Id":2369,"Name":"Puissante Ceinture Fulgurante","CraftCost":25383,"RuneCost":0,"ResellPrice":69729,"Renta":44346,"Date":"29/06/2025"},{"Id":2532,"Name":"Caracape","CraftCost":10244,"RuneCost":0,"ResellPrice":40815,"Renta":30571,"Date":"29/06/2025"},{"Id":706,"Name":"Crystal O'Boul","CraftCost":39228,"RuneCost":0,"ResellPrice":59999,"Renta":20771,"Date":"29/06/2025"},{"Id":8152,"Name":"Ceinture du Craqueleur Légendaire","CraftCost":36356,"RuneCost":0,"ResellPrice":60699,"Renta":24343,"Date":"29/06/2025"},{"Id":7216,"Name":"Sandales Koliques","CraftCost":11841,"RuneCost":0,"ResellPrice":44499,"Renta":32658,"Date":"29/06/2025"},{"Id":19092,"Name":"Pagne du Muloubar","CraftCost":29192,"RuneCost":0,"ResellPrice":46999,"Renta":17807,"Date":"29/06/2025"},{"Id":11378,"Name":"Plumodales","CraftCost":4566,"RuneCost":0,"ResellPrice":24099,"Renta":19533,"Date":"29/06/2025"},{"Id":13017,"Name":"Ceinturoduvet","CraftCost":10090,"RuneCost":0,"ResellPrice":261999,"Renta":251909,"Date":"29/06/2025"},{"Id":14073,"Name":"Coiffe du Kanimate","CraftCost":1305425,"RuneCost":0,"ResellPrice":1999998,"Renta":694573,"Date":"29/06/2025"},{"Id":8325,"Name":"Coiffe du Mominotor","CraftCost":129799,"RuneCost":0,"ResellPrice":279999,"Renta":150200,"Date":"29/06/2025"},{"Id":19082,"Name":"Cape du Scorbute","CraftCost":12407,"RuneCost":0,"ResellPrice":89999,"Renta":77592,"Date":"29/06/2025"},{"Id":7145,"Name":"Coiffe du Gaddie","CraftCost":70529,"RuneCost":0,"ResellPrice":111997,"Renta":41468,"Date":"29/06/2025"},{"Id":7152,"Name":"Kanistère","CraftCost":62051,"RuneCost":0,"ResellPrice":98999,"Renta":36948,"Date":"29/06/2025"},{"Id":8007,"Name":"Cape du Koalak","CraftCost":9130,"RuneCost":0,"ResellPrice":44894,"Renta":35764,"Date":"29/06/2025"},{"Id":8163,"Name":"Kabuto","CraftCost":63806,"RuneCost":0,"ResellPrice":94999,"Renta":31193,"Date":"29/06/2025"},{"Id":11727,"Name":"Cape Peupret","CraftCost":616347,"RuneCost":0,"ResellPrice":799999,"Renta":183652,"Date":"29/06/2025"},{"Id":14885,"Name":"Cape Parition","CraftCost":899614,"RuneCost":0,"ResellPrice":1584999,"Renta":685385,"Date":"29/06/2025"},{"Id":14050,"Name":"Masque de Klime","CraftCost":323619,"RuneCost":0,"ResellPrice":931999,"Renta":608380,"Date":"29/06/2025"},{"Id":15359,"Name":"Gruchape","CraftCost":155003,"RuneCost":0,"ResellPrice":449999,"Renta":294996,"Date":"29/06/2025"},{"Id":8280,"Name":"Cape du Minotot","CraftCost":260804,"RuneCost":0,"ResellPrice":389998,"Renta":129194,"Date":"29/06/2025"},{"Id":6989,"Name":"Krokop","CraftCost":48299,"RuneCost":0,"ResellPrice":79899,"Renta":31600,"Date":"29/06/2025"},{"Id":8009,"Name":"Coiffe du Koalak","CraftCost":14468,"RuneCost":0,"ResellPrice":39999,"Renta":25531,"Date":"29/06/2025"},{"Id":14880,"Name":"Casquipik","CraftCost":758667,"RuneCost":0,"ResellPrice":983999,"Renta":225332,"Date":"29/06/2025"},{"Id":8926,"Name":"Dagues Adou","CraftCost":349067,"RuneCost":0,"ResellPrice":1749999,"Renta":1400932,"Date":"29/06/2025"},{"Id":2373,"Name":"Moon Boutse","CraftCost":20788,"RuneCost":0,"ResellPrice":61456,"Renta":40668,"Date":"29/06/2025"},{"Id":1665,"Name":"Bottes d'Apprentissage","CraftCost":16515,"RuneCost":0,"ResellPrice":38899,"Renta":22384,"Date":"29/06/2025"},{"Id":2532,"Name":"Caracape","CraftCost":10777,"RuneCost":0,"ResellPrice":40815,"Renta":30038,"Date":"29/06/2025"},{"Id":1085,"Name":"Marteau des Falistos","CraftCost":10914,"RuneCost":0,"ResellPrice":29998,"Renta":19084,"Date":"29/06/2025"},{"Id":333,"Name":"Baguette Deuh-Pain","CraftCost":14567,"RuneCost":0,"ResellPrice":35698,"Renta":21131,"Date":"29/06/2025"},{"Id":6528,"Name":"Pelle Rinage","CraftCost":42600,"RuneCost":0,"ResellPrice":74999,"Renta":32399,"Date":"29/06/2025"},{"Id":6481,"Name":"Dora Bora","CraftCost":226168,"RuneCost":0,"ResellPrice":305999,"Renta":79831,"Date":"29/06/2025"},{"Id":6830,"Name":"Petit sac d'écolier du Chef Crocodaille","CraftCost":13382,"RuneCost":0,"ResellPrice":29999,"Renta":16617,"Date":"29/06/2025"},{"Id":6712,"Name":"Cape Hucine","CraftCost":11928,"RuneCost":0,"ResellPrice":21999,"Renta":10071,"Date":"29/06/2025"},{"Id":6764,"Name":"Fourbacoiffe","CraftCost":59278,"RuneCost":0,"ResellPrice":77249,"Renta":17971,"Date":"29/06/2025"},{"Id":8931,"Name":"Az'tech","CraftCost":372028,"RuneCost":0,"ResellPrice":799999,"Renta":427971,"Date":"30/06/2025"},{"Id":8094,"Name":"L'Epée Rilleuse","CraftCost":538279,"RuneCost":0,"ResellPrice":899999,"Renta":361720,"Date":"30/06/2025"},{"Id":8420,"Name":"Pelle Dragoeuf","CraftCost":88211,"RuneCost":0,"ResellPrice":124999,"Renta":36788,"Date":"30/06/2025"},{"Id":9176,"Name":"Lame Assacre","CraftCost":568738,"RuneCost":0,"ResellPrice":979999,"Renta":411261,"Date":"30/06/2025"},{"Id":8596,"Name":"Griffe Pourpre","CraftCost":163417,"RuneCost":0,"ResellPrice":287998,"Renta":124581,"Date":"30/06/2025"},{"Id":9117,"Name":"Ougarteau","CraftCost":688136,"RuneCost":0,"ResellPrice":977999,"Renta":289863,"Date":"30/06/2025"},{"Id":11820,"Name":"Pelle Vétik","CraftCost":320230,"RuneCost":0,"ResellPrice":634999,"Renta":314769,"Date":"30/06/2025"},{"Id":11754,"Name":"Arc Ontanporin","CraftCost":490564,"RuneCost":0,"ResellPrice":799999,"Renta":309435,"Date":"30/06/2025"},{"Id":11758,"Name":"Baguette Hernelle","CraftCost":391054,"RuneCost":0,"ResellPrice":730999,"Renta":339945,"Date":"30/06/2025"},{"Id":7207,"Name":"Bâton du Yondanwa","CraftCost":22119,"RuneCost":0,"ResellPrice":116999,"Renta":94880,"Date":"30/06/2025"},{"Id":8005,"Name":"Arc du Koalak","CraftCost":18033,"RuneCost":0,"ResellPrice":79999,"Renta":61966,"Date":"30/06/2025"},{"Id":7171,"Name":"Baguette Ourderie","CraftCost":64249,"RuneCost":0,"ResellPrice":339999,"Renta":275750,"Date":"30/06/2025"},{"Id":11756,"Name":"Arc Ahique","CraftCost":591945,"RuneCost":0,"ResellPrice":821999,"Renta":230054,"Date":"30/06/2025"},{"Id":8608,"Name":"La Bastonneuze","CraftCost":20696,"RuneCost":0,"ResellPrice":64849,"Renta":44153,"Date":"30/06/2025"},{"Id":7161,"Name":"Arc Assin","CraftCost":28159,"RuneCost":0,"ResellPrice":139719,"Renta":111560,"Date":"30/06/2025"},{"Id":7170,"Name":"Baguette Houffe-Craitien","CraftCost":65866,"RuneCost":0,"ResellPrice":97998,"Renta":32132,"Date":"30/06/2025"},{"Id":9135,"Name":"Baguetterelle","CraftCost":340796,"RuneCost":0,"ResellPrice":675999,"Renta":335203,"Date":"30/06/2025"},{"Id":8103,"Name":"Arc Rainier","CraftCost":81982,"RuneCost":0,"ResellPrice":114999,"Renta":33017,"Date":"30/06/2025"},{"Id":270,"Name":"Xaveur","CraftCost":16489,"RuneCost":0,"ResellPrice":45999,"Renta":29510,"Date":"30/06/2025"},{"Id":333,"Name":"Baguette Deuh-Pain","CraftCost":14498,"RuneCost":0,"ResellPrice":41399,"Renta":26901,"Date":"30/06/2025"},{"Id":2808,"Name":"Ceinture Dracochoune","CraftCost":21933,"RuneCost":0,"ResellPrice":244999,"Renta":223066,"Date":"01/07/2025"},{"Id":1665,"Name":"Bottes d'Apprentissage","CraftCost":16672,"RuneCost":0,"ResellPrice":42998,"Renta":26326,"Date":"01/07/2025"},{"Id":968,"Name":"Ceinture Fulgurante","CraftCost":12170,"RuneCost":0,"ResellPrice":24999,"Renta":12829,"Date":"01/07/2025"},{"Id":2532,"Name":"Caracape","CraftCost":9839,"RuneCost":0,"ResellPrice":37769,"Renta":27930,"Date":"01/07/2025"},{"Id":971,"Name":"Cape du Wa Wabbit","CraftCost":14631,"RuneCost":0,"ResellPrice":25899,"Renta":11268,"Date":"01/07/2025"},{"Id":2544,"Name":"Corbalame","CraftCost":53316,"RuneCost":0,"ResellPrice":130999,"Renta":77683,"Date":"01/07/2025"},{"Id":1085,"Name":"Marteau des Falistos","CraftCost":6960,"RuneCost":0,"ResellPrice":29998,"Renta":23038,"Date":"01/07/2025"},{"Id":1431,"Name":"Pelle Mechba","CraftCost":3315,"RuneCost":0,"ResellPrice":16499,"Renta":13184,"Date":"01/07/2025"},{"Id":1162,"Name":"Bâton des Rois","CraftCost":18738,"RuneCost":0,"ResellPrice":59999,"Renta":41261,"Date":"01/07/2025"},{"Id":970,"Name":"Bâton du Wa Wabbit","CraftCost":10399,"RuneCost":0,"ResellPrice":25497,"Renta":15098,"Date":"01/07/2025"},{"Id":2808,"Name":"Ceinture Dracochoune","CraftCost":19895,"RuneCost":0,"ResellPrice":244999,"Renta":225104,"Date":"01/07/2025"},{"Id":969,"Name":"Couronne du Wa Wabbit","CraftCost":15037,"RuneCost":0,"ResellPrice":29292,"Renta":14255,"Date":"01/07/2025"},{"Id":971,"Name":"Cape du Wa Wabbit","CraftCost":14921,"RuneCost":0,"ResellPrice":28997,"Renta":14076,"Date":"01/07/2025"},{"Id":233,"Name":"Kaiser","CraftCost":63174,"RuneCost":0,"ResellPrice":222221,"Renta":159047,"Date":"01/07/2025"},{"Id":1162,"Name":"Bâton des Rois","CraftCost":21348,"RuneCost":0,"ResellPrice":69898,"Renta":48550,"Date":"01/07/2025"},{"Id":970,"Name":"Bâton du Wa Wabbit","CraftCost":10709,"RuneCost":0,"ResellPrice":25499,"Renta":14790,"Date":"01/07/2025"},{"Id":1140,"Name":"Baguette d'Houvette","CraftCost":7263,"RuneCost":0,"ResellPrice":19999,"Renta":12736,"Date":"01/07/2025"},{"Id":8933,"Name":"Hache Sueur Rance","CraftCost":201096,"RuneCost":0,"ResellPrice":777774,"Renta":576678,"Date":"02/07/2025"},{"Id":13848,"Name":"Couteau de Mer","CraftCost":130722,"RuneCost":0,"ResellPrice":178999,"Renta":48277,"Date":"02/07/2025"},{"Id":7159,"Name":"Marteau Pinière","CraftCost":71184,"RuneCost":0,"ResellPrice":118999,"Renta":47815,"Date":"02/07/2025"},{"Id":7202,"Name":"Sabre Sandanwa","CraftCost":60520,"RuneCost":0,"ResellPrice":70999,"Renta":10479,"Date":"02/07/2025"},{"Id":7198,"Name":"Razoir du Soir","CraftCost":62172,"RuneCost":0,"ResellPrice":93999,"Renta":31827,"Date":"02/07/2025"},{"Id":15768,"Name":"Anneau de XLII","CraftCost":552294,"RuneCost":0,"ResellPrice":621319,"Renta":69025,"Date":"02/07/2025"},{"Id":27526,"Name":"Anneau Clochecuivre","CraftCost":413419,"RuneCost":0,"ResellPrice":1099999,"Renta":686580,"Date":"02/07/2025"},{"Id":13636,"Name":"Amulette de Nevark","CraftCost":703627,"RuneCost":0,"ResellPrice":1099999,"Renta":396372,"Date":"02/07/2025"},{"Id":13170,"Name":"Amulette de Pwâk","CraftCost":281600,"RuneCost":0,"ResellPrice":697349,"Renta":415749,"Date":"02/07/2025"},{"Id":9128,"Name":"Blopanneau Coco Royal","CraftCost":5761,"RuneCost":0,"ResellPrice":99999,"Renta":94238,"Date":"02/07/2025"},{"Id":10852,"Name":"Amulette d'Hulkrap","CraftCost":14582,"RuneCost":0,"ResellPrice":60599,"Renta":46017,"Date":"02/07/2025"},{"Id":13642,"Name":"Anneau de Padgref","CraftCost":1266299,"RuneCost":0,"ResellPrice":1745010,"Renta":478711,"Date":"02/07/2025"},{"Id":27538,"Name":"Collier Gris","CraftCost":707247,"RuneCost":0,"ResellPrice":1099998,"Renta":392751,"Date":"02/07/2025"},{"Id":20851,"Name":"Ceinture Amincissante","CraftCost":280990,"RuneCost":0,"ResellPrice":1499999,"Renta":1219009,"Date":"02/07/2025"},{"Id":11716,"Name":"Ceinture de Kolosso","CraftCost":280281,"RuneCost":0,"ResellPrice":1489999,"Renta":1209718,"Date":"02/07/2025"},{"Id":20982,"Name":"Bottes Croquantes","CraftCost":1421304,"RuneCost":0,"ResellPrice":2499999,"Renta":1078695,"Date":"02/07/2025"},{"Id":13116,"Name":"Bottes de Brouce","CraftCost":634419,"RuneCost":0,"ResellPrice":1294999,"Renta":660580,"Date":"02/07/2025"},{"Id":9167,"Name":"Blopture Griotte","CraftCost":8003,"RuneCost":0,"ResellPrice":499999,"Renta":491996,"Date":"02/07/2025"},{"Id":12416,"Name":"Ceinture de Grozilla","CraftCost":943421,"RuneCost":0,"ResellPrice":1299999,"Renta":356578,"Date":"02/07/2025"},{"Id":8726,"Name":"Chaussures Lepon-Davignon","CraftCost":51375,"RuneCost":0,"ResellPrice":234999,"Renta":183624,"Date":"02/07/2025"},{"Id":9164,"Name":"Bloptes Coco Royales","CraftCost":13014,"RuneCost":0,"ResellPrice":99999,"Renta":86985,"Date":"02/07/2025"},{"Id":11721,"Name":"Ceinture du Glourséleste","CraftCost":299983,"RuneCost":0,"ResellPrice":1211110,"Renta":911127,"Date":"02/07/2025"},{"Id":14930,"Name":"Obscture","CraftCost":1309448,"RuneCost":0,"ResellPrice":1748999,"Renta":439551,"Date":"02/07/2025"},{"Id":11719,"Name":"Cape du Glourséleste","CraftCost":551620,"RuneCost":0,"ResellPrice":1399998,"Renta":848378,"Date":"02/07/2025"},{"Id":12108,"Name":"Cape du Professeur Xa","CraftCost":647053,"RuneCost":0,"ResellPrice":1297999,"Renta":650946,"Date":"02/07/2025"},{"Id":27525,"Name":"Heaume Clochecuivre","CraftCost":1183154,"RuneCost":0,"ResellPrice":1776999,"Renta":593845,"Date":"02/07/2025"},{"Id":23626,"Name":"Bandeau de Spiritueur","CraftCost":487122,"RuneCost":0,"ResellPrice":1079999,"Renta":592877,"Date":"02/07/2025"},{"Id":11726,"Name":"Cape Surde","CraftCost":428216,"RuneCost":0,"ResellPrice":888887,"Renta":460671,"Date":"02/07/2025"},{"Id":13120,"Name":"Coiffe de Danathor","CraftCost":750558,"RuneCost":0,"ResellPrice":999999,"Renta":249441,"Date":"02/07/2025"},{"Id":8935,"Name":"La Bêche à Mel","CraftCost":199415,"RuneCost":0,"ResellPrice":2595699,"Renta":2396284,"Date":"02/07/2025"},{"Id":8929,"Name":"Kriss Toubal","CraftCost":132035,"RuneCost":0,"ResellPrice":569999,"Renta":437964,"Date":"02/07/2025"},{"Id":27540,"Name":"Marteau Aigri","CraftCost":860221,"RuneCost":0,"ResellPrice":1199999,"Renta":339778,"Date":"02/07/2025"},{"Id":8148,"Name":"Marteau du Craqueleur Légendaire","CraftCost":34130,"RuneCost":0,"ResellPrice":289999,"Renta":255869,"Date":"02/07/2025"},{"Id":27528,"Name":"Masse Clochecuivre","CraftCost":884389,"RuneCost":0,"ResellPrice":2399998,"Renta":1515609,"Date":"02/07/2025"},{"Id":8834,"Name":"Branche de l'Abrakleur sombre","CraftCost":130863,"RuneCost":0,"ResellPrice":799999,"Renta":669136,"Date":"02/07/2025"},{"Id":20848,"Name":"Sceptre Zor","CraftCost":280707,"RuneCost":0,"ResellPrice":889999,"Renta":609292,"Date":"02/07/2025"},{"Id":12103,"Name":"Arc de Guten Tak","CraftCost":419909,"RuneCost":0,"ResellPrice":799998,"Renta":380089,"Date":"02/07/2025"},{"Id":1665,"Name":"Bottes d'Apprentissage","CraftCost":16412,"RuneCost":0,"ResellPrice":42998,"Renta":26586,"Date":"02/07/2025"},{"Id":1132,"Name":"Baguette Ni'Ninnin","CraftCost":22552,"RuneCost":0,"ResellPrice":237999,"Renta":215447,"Date":"02/07/2025"},{"Id":1162,"Name":"Bâton des Rois","CraftCost":19488,"RuneCost":0,"ResellPrice":69999,"Renta":50511,"Date":"02/07/2025"},{"Id":9155,"Name":"Amublop Coco Royale","CraftCost":12711,"RuneCost":0,"ResellPrice":87998,"Renta":75287,"Date":"02/07/2025"},{"Id":18433,"Name":"Cacture","CraftCost":159201,"RuneCost":0,"ResellPrice":424999,"Renta":265798,"Date":"02/07/2025"},{"Id":27554,"Name":"Jambières Hitaj","CraftCost":50701,"RuneCost":0,"ResellPrice":199984,"Renta":149283,"Date":"02/07/2025"},{"Id":12093,"Name":"Cape de Cantile","CraftCost":114499,"RuneCost":0,"ResellPrice":349999,"Renta":235500,"Date":"02/07/2025"},{"Id":7245,"Name":"Geta Aerdala","CraftCost":3994,"RuneCost":0,"ResellPrice":65799,"Renta":61805,"Date":"02/07/2025"},{"Id":7001,"Name":"Talisman du Faucheur d'Avoine","CraftCost":5958,"RuneCost":0,"ResellPrice":49998,"Renta":44040,"Date":"02/07/2025"},{"Id":7251,"Name":"Amulette Terrdala","CraftCost":34907,"RuneCost":0,"ResellPrice":74999,"Renta":40092,"Date":"02/07/2025"},{"Id":6743,"Name":"Fourballiance","CraftCost":58435,"RuneCost":0,"ResellPrice":145999,"Renta":87564,"Date":"02/07/2025"},{"Id":6997,"Name":"Anneau Fioutioure","CraftCost":8625,"RuneCost":0,"ResellPrice":39999,"Renta":31374,"Date":"02/07/2025"},{"Id":7249,"Name":"Alliance Aerdala","CraftCost":15797,"RuneCost":0,"ResellPrice":39099,"Renta":23302,"Date":"02/07/2025"},{"Id":6817,"Name":"Amulette du Chef Crocodaille","CraftCost":19640,"RuneCost":0,"ResellPrice":40399,"Renta":20759,"Date":"02/07/2025"},{"Id":7253,"Name":"Amulette Aerdala","CraftCost":10650,"RuneCost":0,"ResellPrice":47998,"Renta":37348,"Date":"02/07/2025"},{"Id":7247,"Name":"Alliance Terrdala","CraftCost":35111,"RuneCost":0,"ResellPrice":67999,"Renta":32888,"Date":"02/07/2025"},{"Id":7555,"Name":"Anodindo","CraftCost":3235,"RuneCost":0,"ResellPrice":18299,"Renta":15064,"Date":"02/07/2025"},{"Id":7559,"Name":"Goldoture","CraftCost":268546,"RuneCost":0,"ResellPrice":397999,"Renta":129453,"Date":"02/07/2025"},{"Id":1665,"Name":"Bottes d'Apprentissage","CraftCost":15529,"RuneCost":0,"ResellPrice":43433,"Renta":27904,"Date":"02/07/2025"},{"Id":7215,"Name":"Sandales Humeuses","CraftCost":66140,"RuneCost":0,"ResellPrice":87996,"Renta":21856,"Date":"02/07/2025"},{"Id":7244,"Name":"Geta Feudala","CraftCost":18145,"RuneCost":0,"ResellPrice":39999,"Renta":21854,"Date":"02/07/2025"},{"Id":7240,"Name":"Ceinture Feudala","CraftCost":24202,"RuneCost":0,"ResellPrice":44999,"Renta":20797,"Date":"02/07/2025"},{"Id":2687,"Name":"Ceinture Tortue Rouge","CraftCost":16620,"RuneCost":0,"ResellPrice":44499,"Renta":27879,"Date":"02/07/2025"},{"Id":7141,"Name":"Holoune","CraftCost":105145,"RuneCost":0,"ResellPrice":169998,"Renta":64853,"Date":"02/07/2025"},{"Id":6834,"Name":"Coiffe du Chef Crocodaille","CraftCost":21076,"RuneCost":0,"ResellPrice":64999,"Renta":43923,"Date":"02/07/2025"},{"Id":6764,"Name":"Fourbacoiffe","CraftCost":54626,"RuneCost":0,"ResellPrice":94999,"Renta":40373,"Date":"02/07/2025"},{"Id":6500,"Name":"Oreilles de Wabbits","CraftCost":11037,"RuneCost":0,"ResellPrice":51514,"Renta":40477,"Date":"02/07/2025"},{"Id":6989,"Name":"Krokop","CraftCost":50095,"RuneCost":0,"ResellPrice":79799,"Renta":29704,"Date":"02/07/2025"},{"Id":6712,"Name":"Cape Hucine","CraftCost":12524,"RuneCost":0,"ResellPrice":28998,"Renta":16474,"Date":"02/07/2025"},{"Id":6954,"Name":"Cape du Mulou","CraftCost":11915,"RuneCost":0,"ResellPrice":23998,"Renta":12083,"Date":"02/07/2025"},{"Id":7232,"Name":"Cape Feudala","CraftCost":13870,"RuneCost":0,"ResellPrice":24899,"Renta":11029,"Date":"02/07/2025"},{"Id":7516,"Name":"Coiffe du Bimd'Oule","CraftCost":90482,"RuneCost":0,"ResellPrice":118999,"Renta":28517,"Date":"02/07/2025"},{"Id":7152,"Name":"Kanistère","CraftCost":57486,"RuneCost":0,"ResellPrice":79999,"Renta":22513,"Date":"02/07/2025"},{"Id":7255,"Name":"Hache Terrdala","CraftCost":29742,"RuneCost":0,"ResellPrice":109999,"Renta":80257,"Date":"02/07/2025"},{"Id":6511,"Name":"Marteau Ridhe","CraftCost":45923,"RuneCost":0,"ResellPrice":89989,"Renta":44066,"Date":"02/07/2025"},{"Id":1427,"Name":"Pelle Zébuth","CraftCost":7709,"RuneCost":0,"ResellPrice":29999,"Renta":22290,"Date":"02/07/2025"},{"Id":7256,"Name":"Dagues Aerdala","CraftCost":13610,"RuneCost":0,"ResellPrice":34499,"Renta":20889,"Date":"02/07/2025"},{"Id":7257,"Name":"Sabre Feudala","CraftCost":31597,"RuneCost":0,"ResellPrice":75499,"Renta":43902,"Date":"02/07/2025"},{"Id":7157,"Name":"Marteau Ksain","CraftCost":68968,"RuneCost":0,"ResellPrice":94999,"Renta":26031,"Date":"02/07/2025"},{"Id":3648,"Name":"Daguette du Captain Chafer","CraftCost":27434,"RuneCost":0,"ResellPrice":38999,"Renta":11565,"Date":"02/07/2025"},{"Id":7210,"Name":"Hache du Sandanwa","CraftCost":17639,"RuneCost":0,"ResellPrice":27776,"Renta":10137,"Date":"02/07/2025"},{"Id":7170,"Name":"Baguette Houffe-Craitien","CraftCost":61807,"RuneCost":0,"ResellPrice":98886,"Renta":37079,"Date":"02/07/2025"},{"Id":333,"Name":"Baguette Deuh-Pain","CraftCost":13263,"RuneCost":0,"ResellPrice":42089,"Renta":28826,"Date":"02/07/2025"},{"Id":6496,"Name":"Baguette en Racine d'Abraknyde Sombre","CraftCost":12503,"RuneCost":0,"ResellPrice":23999,"Renta":11496,"Date":"02/07/2025"},{"Id":7181,"Name":"Racine Sémilla","CraftCost":24448,"RuneCost":0,"ResellPrice":46999,"Renta":22551,"Date":"02/07/2025"},{"Id":14006,"Name":"Infernano","CraftCost":274649,"RuneCost":0,"ResellPrice":615878,"Renta":341229,"Date":"02/07/2025"},{"Id":14058,"Name":"Anneau Glacial","CraftCost":640353,"RuneCost":0,"ResellPrice":947999,"Renta":307646,"Date":"02/07/2025"},{"Id":14007,"Name":"Styxano","CraftCost":253404,"RuneCost":0,"ResellPrice":599999,"Renta":346595,"Date":"02/07/2025"},{"Id":17587,"Name":"Col de Ush","CraftCost":418994,"RuneCost":0,"ResellPrice":699998,"Renta":281004,"Date":"02/07/2025"},{"Id":15762,"Name":"Bottes de XLII","CraftCost":420891,"RuneCost":0,"ResellPrice":759999,"Renta":339108,"Date":"02/07/2025"},{"Id":13118,"Name":"Bottes d'Otomaï","CraftCost":785044,"RuneCost":0,"ResellPrice":1089999,"Renta":304955,"Date":"02/07/2025"},{"Id":11473,"Name":"Frimature","CraftCost":897281,"RuneCost":0,"ResellPrice":1199999,"Renta":302718,"Date":"02/07/2025"},{"Id":12089,"Name":"Amulette de Frigostine","CraftCost":204801,"RuneCost":0,"ResellPrice":438999,"Renta":234198,"Date":"02/07/2025"},{"Id":11579,"Name":"Bague de l'Obsidiantre","CraftCost":394437,"RuneCost":0,"ResellPrice":599999,"Renta":205562,"Date":"02/07/2025"},{"Id":11622,"Name":"Anneau Nobstant","CraftCost":131682,"RuneCost":0,"ResellPrice":339998,"Renta":208316,"Date":"02/07/2025"},{"Id":12100,"Name":"Anneau de Guten Tak","CraftCost":457135,"RuneCost":0,"ResellPrice":649999,"Renta":192864,"Date":"02/07/2025"},{"Id":11738,"Name":"Anneau Aimgéroks","CraftCost":300858,"RuneCost":0,"ResellPrice":797999,"Renta":497141,"Date":"02/07/2025"},{"Id":26309,"Name":"Bottes Crépitantes de Malter","CraftCost":376083,"RuneCost":0,"ResellPrice":674999,"Renta":298916,"Date":"02/07/2025"},{"Id":17588,"Name":"Bottes de Ush","CraftCost":845608,"RuneCost":0,"ResellPrice":1486079,"Renta":640471,"Date":"02/07/2025"},{"Id":10438,"Name":"Les Maidartes","CraftCost":254229,"RuneCost":0,"ResellPrice":448999,"Renta":194770,"Date":"02/07/2025"},{"Id":13638,"Name":"Cape de Théodoran Ax","CraftCost":776750,"RuneCost":0,"ResellPrice":1088999,"Renta":312249,"Date":"02/07/2025"},{"Id":8366,"Name":"Cape du Petit Chapon Rouge","CraftCost":204144,"RuneCost":0,"ResellPrice":499998,"Renta":295854,"Date":"02/07/2025"},{"Id":23628,"Name":"Fût d'Aspiratueur","CraftCost":267013,"RuneCost":0,"ResellPrice":549999,"Renta":282986,"Date":"02/07/2025"},{"Id":8441,"Name":"Billréole","CraftCost":67635,"RuneCost":0,"ResellPrice":349998,"Renta":282363,"Date":"02/07/2025"},{"Id":15061,"Name":"Cape du Kaniblou","CraftCost":478993,"RuneCost":0,"ResellPrice":749998,"Renta":271005,"Date":"02/07/2025"},{"Id":6501,"Name":"Sac-Cawotte","CraftCost":12825,"RuneCost":0,"ResellPrice":269999,"Renta":257174,"Date":"02/07/2025"},{"Id":13123,"Name":"Couronne d'Allister","CraftCost":439408,"RuneCost":0,"ResellPrice":699994,"Renta":260586,"Date":"02/07/2025"},{"Id":8828,"Name":"Perruque du Poolay","CraftCost":411551,"RuneCost":0,"ResellPrice":599999,"Renta":188448,"Date":"02/07/2025"},{"Id":23627,"Name":"Katana de Spiritueur","CraftCost":386490,"RuneCost":0,"ResellPrice":699999,"Renta":313509,"Date":"02/07/2025"},{"Id":14287,"Name":"Pendentif Oton","CraftCost":1042570,"RuneCost":0,"ResellPrice":1398989,"Renta":356419,"Date":"03/07/2025"},{"Id":11731,"Name":"Amulette Hendart","CraftCost":697938,"RuneCost":0,"ResellPrice":1446999,"Renta":749061,"Date":"03/07/2025"},{"Id":12068,"Name":"Ceinture Bine","CraftCost":579925,"RuneCost":0,"ResellPrice":854999,"Renta":275074,"Date":"03/07/2025"},{"Id":15060,"Name":"Ceinture du Kaniblou","CraftCost":294058,"RuneCost":0,"ResellPrice":489998,"Renta":195940,"Date":"03/07/2025"},{"Id":23260,"Name":"Capistil","CraftCost":103387,"RuneCost":0,"ResellPrice":284999,"Renta":181612,"Date":"03/07/2025"},{"Id":8101,"Name":"Le Fendoir Tichaud","CraftCost":136762,"RuneCost":0,"ResellPrice":333999,"Renta":197237,"Date":"03/07/2025"},{"Id":1359,"Name":"Le Tison Fûté","CraftCost":6595,"RuneCost":0,"ResellPrice":19999,"Renta":13404,"Date":"03/07/2025"},{"Id":2369,"Name":"Puissante Ceinture Fulgurante","CraftCost":25923,"RuneCost":0,"ResellPrice":86999,"Renta":61076,"Date":"03/07/2025"},{"Id":1665,"Name":"Bottes d'Apprentissage","CraftCost":15850,"RuneCost":0,"ResellPrice":42999,"Renta":27149,"Date":"03/07/2025"},{"Id":2532,"Name":"Caracape","CraftCost":8414,"RuneCost":0,"ResellPrice":40814,"Renta":32400,"Date":"03/07/2025"},{"Id":270,"Name":"Xaveur","CraftCost":17389,"RuneCost":0,"ResellPrice":63199,"Renta":45810,"Date":"03/07/2025"},{"Id":657,"Name":"Bâton du Maître des Tofus","CraftCost":8489,"RuneCost":0,"ResellPrice":18499,"Renta":10010,"Date":"03/07/2025"},{"Id":13118,"Name":"Bottes d'Otomaï","CraftCost":784696,"RuneCost":0,"ResellPrice":999999,"Renta":215303,"Date":"03/07/2025"},{"Id":8268,"Name":"Collier du Minotoror","CraftCost":190351,"RuneCost":0,"ResellPrice":499999,"Renta":309648,"Date":"03/07/2025"},{"Id":6481,"Name":"Dora Bora","CraftCost":229137,"RuneCost":0,"ResellPrice":299998,"Renta":70861,"Date":"03/07/2025"},{"Id":15200,"Name":"Cape Phossile","CraftCost":184745,"RuneCost":0,"ResellPrice":297999,"Renta":113254,"Date":"03/07/2025"},{"Id":11571,"Name":"Coiffe du Royalmouth","CraftCost":164867,"RuneCost":0,"ResellPrice":269999,"Renta":105132,"Date":"03/07/2025"},{"Id":8450,"Name":"Rapière du Rat Blanc","CraftCost":68771,"RuneCost":0,"ResellPrice":204999,"Renta":136228,"Date":"03/07/2025"},{"Id":16169,"Name":"Vieille Branche du Chêne Mou","CraftCost":96164,"RuneCost":0,"ResellPrice":229998,"Renta":133834,"Date":"03/07/2025"}],"nbKamasInvesti":1689817611,"EstimationKamasGagnes":2936924386,"RentaNet":1247106775,"RentaPercentage":1.738012651118}]